{"id": "SES016738", "tunefamily": "", "year": -1, "tunefamily_full": "", "type": "", "freemeter": false, "origin": "", "features": {"scaledegree": [1, 5, 1, 6, 1, 5, 6, 1, 3, 5, 3, 4, 3, 2, 3, 1, 3, 3, 5, 4, 3, 2, 1, 6, 6, 5, 6, 5, 3, 2, 1, 5, 1, 6, 1, 5, 6, 1, 3, 5, 3, 4, 3, 2, 3, 1, 3, 6, 3, 5, 3, 3, 2, 1, 7, 2, 1, 4, 3, 2, 2, 1, 7, 2, 1, 4, 3, 2, 3, 1, 5, 4, 3, 5, 1, 3, 2, 5, 5, 2, 5, 2, 4, 3, 2, 1, 6, 6, 5, 3, 5, 6, 7, 1, 5, 3, 3, 2, 2, 4, 3, 1, 5, 4, 3, 5, 1, 3, 2, 5, 5, 2, 5, 2, 3, 4, 3, 2, 7, 1, 2, 1, 6, 5, 6, 1, 2, 3, 1, 1, 4, 5, 6, 1, 2, 3, 1, 5, 3], "scaledegreespecifier": ["P", "P", "P", "M", "P", "P", "M", "P", "M", "P", "M", "P", "M", "M", "M", "P", "M", "M", "P", "P", "M", "M", "P", "M", "M", "P", "M", "P", "M", "M", "P", "P", "P", "M", "P", "P", "M", "P", "M", "P", "M", "P", "M", "M", "M", "P", "M", "M", "M", "P", "M", "M", "M", "P", "M", "M", "P", "P", "M", "M", "M", "P", "M", "M", "P", "P", "M", "M", "M", "P", "P", "P", "M", "P", "P", "M", "M", "P", "P", "M", "P", "M", "P", "M", "M", "P", "M", "M", "P", "M", "P", "M", "M", "P", "P", "M", "M", "M", "M", "P", "M", "P", "P", "P", "M", "P", "P", "M", "M", "P", "P", "M", "P", "M", "M", "P", "M", "M", "M", "P", "M", "P", "M", "P", "M", "P", "M", "M", "P", "P", "P", "P", "M", "P", "M", "M", "P", "P", "M"], "tonic": ["D", "D", "D", "D", "D", "D", "D", "D", "D", "D", "D", "D", "D", "D", "D", "D", "D", "D", "D", "D", "D", "D", "D", "D", "D", "D", "D", "D", "D", "D", "D", "D", "D", "D", "D", "D", "D", "D", "D", "D", "D", "D", "D", "D", "D", "D", "D", "D", "D", "D", "D", "D", "D", "D", "D", "D", "D", "D", "D", "D", "D", "D", "D", "D", "D", "D", "D", "D", "D", "D", "D", "D", "D", "D", "D", "D", "D", "D", "D", "D", "D", "D", "D", "D", "D", "D", "D", "D", "D", "D", "D", "D", "D", "D", "D", "D", "D", "D", "D", "D", "D", "D", "D", "D", "D", "D", "D", "D", "D", "D", "D", "D", "D", "D", "D", "D", "D", "D", "D", "D", "D", "D", "D", "D", "D", "D", "D", "D", "D", "D", "D", "D", "D", "D", "D", "D", "D", "D", "D"], "mode": ["major", "major", "major", "major", "major", "major", "major", "major", "major", "major", "major", "major", "major", "major", "major", "major", "major", "major", "major", "major", "major", "major", "major", "major", "major", "major", "major", "major", "major", "major", "major", "major", "major", "major", "major", "major", "major", "major", "major", "major", "major", "major", "major", "major", "major", "major", "major", "major", "major", "major", "major", "major", "major", "major", "major", "major", "major", "major", "major", "major", "major", "major", "major", "major", "major", "major", "major", "major", "major", "major", "major", "major", "major", "major", "major", "major", "major", "major", "major", "major", "major", "major", "major", "major", "major", "major", "major", "major", "major", "major", "major", "major", "major", "major", "major", "major", "major", "major", "major", "major", "major", "major", "major", "major", "major", "major", "major", "major", "major", "major", "major", "major", "major", "major", "major", "major", "major", "major", "major", "major", "major", "major", "major", "major", "major", "major", "major", "major", "major", "major", "major", "major", "major", "major", "major", "major", "major", "major", "major"], "metriccontour": [null, "-", "-", "+", "-", "+", "-", "+", "-", "+", "-", "+", "-", "+", "-", "+", "-", "+", "+", "-", "+", "-", "+", "-", "+", "-", "+", "-", "+", "-", "+", "-", "-", "+", "-", "+", "-", "+", "-", "+", "-", "+", "-", "+", "-", "+", "-", "+", "-", "+", "-", "+", "+", "-", "+", "-", "+", "-", "-", "+", "+", "-", "+", "-", "+", "-", "-", "+", "+", "-", "+", "-", "+", "-", "+", "-", "+", "-", "+", "+", "-", "+", "-", "+", "-", "+", "-", "+", "-", "+", "-", "+", "-", "+", "+", "-", "+", "-", "+", "-", "+", "-", "+", "-", "+", "-", "+", "-", "+", "-", "+", "+", "-", "+", "-", "+", "-", "+", "-", "+", "-", "+", "-", "+", "-", "+", "-", "+", "-", "+", "-", "+", "-", "+", "-", "+", "-", "+", "-"], "imaweight": [0.521978, 0.55446, 0.251778, 0.435036, 0.351972, 0.590175, 0.271978, 0.486425, 0.245152, 0.480608, 0.459438, 0.472366, 0.229476, 0.561571, 0.24693, 0.5383, 0.420491, 0.519716, 0.451519, 0.37201, 0.528927, 0.322075, 0.5202, 0.256626, 0.568681, 0.291694, 0.418552, 0.456529, 0.556076, 0.333064, 0.494829, 0.533129, 0.436975, 0.677279, 0.445055, 0.58872, 0.483516, 0.505818, 0.527957, 0.6351, 0.319974, 0.527311, 0.5585, 0.61086, 0.428571, 0.591952, 0.442793, 0.582418, 0.503717, 0.506303, 0.542986, 0.68552, 0.585165, 0.791855, 0.463963, 0.695217, 0.581933, 0.71671, 0.0361991, 0.577731, 0.670976, 0.50501, 0.786684, 0.678733, 0.571913, 0.789593, 0.040724, 0.398513, 0.738041, 0.486749, 0.638171, 0.437783, 0.68746, 0.383807, 0.827731, 0.452812, 0.547673, 0.44554, 0.831448, 0.804783, 0.611506, 0.85682, 0.527473, 0.779573, 0.50404, 0.904816, 0.526665, 0.781189, 0.483355, 0.919037, 0.477214, 0.771655, 0.0277957, 0.612476, 0.78426, 0.450873, 0.849548, 0.4617, 1.0, 0.535553, 0.669037, 0.50097, 0.886878, 0.484486, 0.836296, 0.563833, 0.866354, 0.489334, 0.838235, 0.49192, 0.874919, 0.685359, 0.521978, 0.787977, 0.36991, 0.762928, 0.463478, 0.808339, 0.395443, 0.672592, 0.381707, 0.891726, 0.430026, 0.636231, 0.43956, 0.746283, 0.412896, 0.792986, 0.32256, 0.828862, 0.414027, 0.648836, 0.511151, 0.894312, 0.297673, 0.658048, 0.476891, 0.856658, 0.365869], "imaweight_spectral": [0.841141, 0.778678, 0.854996, 0.742515, 0.935423, 0.812962, 0.779382, 0.775038, 0.911471, 0.730656, 0.92603, 0.763884, 0.85253, 0.795468, 0.819185, 0.780674, 0.961489, 0.767524, 0.77633, 0.968181, 0.754491, 0.838676, 0.792767, 0.853352, 0.783374, 0.85934, 0.712105, 0.985323, 0.811671, 0.800399, 0.771985, 0.723377, 0.891394, 0.811436, 0.871081, 0.78948, 0.842785, 0.756604, 0.942468, 0.761418, 0.785136, 0.756487, 0.931079, 0.767524, 0.872725, 0.78584, 0.8557, 0.787484, 0.857579, 0.736762, 0.962898, 0.787249, 0.82623, 0.913819, 0.719385, 0.876952, 0.785605, 0.888811, 0.0277093, 0.803804, 0.835623, 0.760362, 0.953622, 0.809323, 0.794059, 0.896208, 0.0309968, 0.784549, 0.899847, 0.809675, 0.830574, 0.79899, 0.837267, 0.766819, 0.973347, 0.777152, 0.76635, 0.816367, 0.922391, 0.865328, 0.797816, 0.870025, 0.818246, 0.827639, 0.747799, 0.928379, 0.796525, 0.803335, 0.770694, 0.907714, 0.76541, 0.847834, 0.0220735, 0.798168, 0.835153, 0.767993, 0.850182, 0.722907, 1.0, 0.812962, 0.732183, 0.765528, 0.885523, 0.770576, 0.90607, 0.772455, 0.865093, 0.803804, 0.847599, 0.762945, 0.910532, 0.771164, 0.792533, 0.92333, 0.717506, 0.884232, 0.835623, 0.872843, 0.770694, 0.822355, 0.720324, 0.962428, 0.843137, 0.755548, 0.767172, 0.905601, 0.749912, 0.870259, 0.750029, 0.867442, 0.808853, 0.837384, 0.778208, 0.970882, 0.751556, 0.775625, 0.776682, 0.946695, 0.757779], "pitch40_hewlett": [129, 112, 129, 118, 129, 112, 118, 129, 141, 152, 141, 146, 141, 135, 141, 129, 141, 141, 152, 186, 181, 175, 169, 158, 158, 152, 158, 152, 141, 135, 129, 112, 129, 118, 129, 112, 118, 129, 141, 152, 141, 146, 141, 135, 141, 129, 141, 158, 141, 152, 141, 141, 135, 129, 124, 135, 129, 146, 141, 135, 135, 129, 124, 135, 129, 186, 181, 175, 181, 169, 152, 146, 141, 152, 169, 181, 175, 152, 152, 175, 152, 175, 186, 181, 175, 169, 158, 158, 152, 141, 152, 158, 164, 169, 152, 141, 141, 135, 135, 186, 181, 169, 152, 146, 141, 152, 169, 181, 175, 152, 152, 175, 152, 175, 181, 186, 181, 175, 164, 169, 175, 169, 158, 152, 158, 169, 175, 181, 169, 169, 186, 152, 158, 169, 175, 181, 169, 152, 141], "pitch40_sapp": [168, 151, 168, 157, 168, 151, 157, 168, 180, 191, 180, 185, 180, 174, 180, 168, 180, 180, 191, 225, 220, 214, 208, 197, 197, 191, 197, 191, 180, 174, 168, 151, 168, 157, 168, 151, 157, 168, 180, 191, 180, 185, 180, 174, 180, 168, 180, 197, 180, 191, 180, 180, 174, 168, 163, 174, 168, 185, 180, 174, 174, 168, 163, 174, 168, 225, 220, 214, 220, 208, 191, 185, 180, 191, 208, 220, 214, 191, 191, 214, 191, 214, 225, 220, 214, 208, 197, 197, 191, 180, 191, 197, 203, 208, 191, 180, 180, 174, 174, 225, 220, 208, 191, 185, 180, 191, 208, 220, 214, 191, 191, 214, 191, 214, 220, 225, 220, 214, 203, 208, 214, 208, 197, 191, 197, 208, 214, 220, 208, 208, 225, 191, 197, 208, 214, 220, 208, 191, 180], "octave": [4, 3, 4, 3, 4, 3, 3, 4, 4, 4, 4, 4, 4, 4, 4, 4, 4, 4, 4, 5, 5, 5, 5, 4, 4, 4, 4, 4, 4, 4, 4, 3, 4, 3, 4, 3, 3, 4, 4, 4, 4, 4, 4, 4, 4, 4, 4, 4, 4, 4, 4, 4, 4, 4, 4, 4, 4, 4, 4, 4, 4, 4, 4, 4, 4, 5, 5, 5, 5, 5, 4, 4, 4, 4, 5, 5, 5, 4, 4, 5, 4, 5, 5, 5, 5, 5, 4, 4, 4, 4, 4, 4, 5, 5, 4, 4, 4, 4, 4, 5, 5, 5, 4, 4, 4, 4, 5, 5, 5, 4, 4, 5, 4, 5, 5, 5, 5, 5, 5, 5, 5, 5, 4, 4, 4, 5, 5, 5, 5, 5, 5, 4, 4, 5, 5, 5, 5, 4, 4], "midipitch": [62, 57, 62, 59, 62, 57, 59, 62, 66, 69, 66, 67, 66, 64, 66, 62, 66, 66, 69, 79, 78, 76, 74, 71, 71, 69, 71, 69, 66, 64, 62, 57, 62, 59, 62, 57, 59, 62, 66, 69, 66, 67, 66, 64, 66, 62, 66, 71, 66, 69, 66, 66, 64, 62, 61, 64, 62, 67, 66, 64, 64, 62, 61, 64, 62, 79, 78, 76, 78, 74, 69, 67, 66, 69, 74, 78, 76, 69, 69, 76, 69, 76, 79, 78, 76, 74, 71, 71, 69, 66, 69, 71, 73, 74, 69, 66, 66, 64, 64, 79, 78, 74, 69, 67, 66, 69, 74, 78, 76, 69, 69, 76, 69, 76, 78, 79, 78, 76, 73, 74, 76, 74, 71, 69, 71, 74, 76, 78, 74, 74, 79, 69, 71, 74, 76, 78, 74, 69, 66], "diatonicpitch": [28, 25, 28, 26, 28, 25, 26, 28, 30, 32, 30, 31, 30, 29, 30, 28, 30, 30, 32, 38, 37, 36, 35, 33, 33, 32, 33, 32, 30, 29, 28, 25, 28, 26, 28, 25, 26, 28, 30, 32, 30, 31, 30, 29, 30, 28, 30, 33, 30, 32, 30, 30, 29, 28, 27, 29, 28, 31, 30, 29, 29, 28, 27, 29, 28, 38, 37, 36, 37, 35, 32, 31, 30, 32, 35, 37, 36, 32, 32, 36, 32, 36, 38, 37, 36, 35, 33, 33, 32, 30, 32, 33, 34, 35, 32, 30, 30, 29, 29, 38, 37, 35, 32, 31, 30, 32, 35, 37, 36, 32, 32, 36, 32, 36, 37, 38, 37, 36, 34, 35, 36, 35, 33, 32, 33, 35, 36, 37, 35, 35, 38, 32, 33, 35, 36, 37, 35, 32, 30], "diatonicinterval": [null, -3, 3, -2, 2, -3, 1, 2, 2, 2, -2, 1, -1, -1, 1, -2, 2, 0, 2, 6, -1, -1, -1, -2, 0, -1, 1, -1, -2, -1, -1, -3, 3, -2, 2, -3, 1, 2, 2, 2, -2, 1, -1, -1, 1, -2, 2, 3, -3, 2, -2, 0, -1, -1, -1, 2, -1, 3, -1, -1, 0, -1, -1, 2, -1, 10, -1, -1, 1, -2, -3, -1, -1, 2, 3, 2, -1, -4, 0, 4, -4, 4, 2, -1, -1, -1, -2, 0, -1, -2, 2, 1, 1, 1, -3, -2, 0, -1, 0, 9, -1, -2, -3, -1, -1, 2, 3, 2, -1, -4, 0, 4, -4, 4, 1, 1, -1, -1, -2, 1, 1, -1, -2, -1, 1, 2, 1, 1, -2, 0, 3, -6, 1, 2, 1, 1, -2, -3, -2], "chromaticinterval": [null, -5, 5, -3, 3, -5, 2, 3, 4, 3, -3, 1, -1, -2, 2, -4, 4, 0, 3, 10, -1, -2, -2, -3, 0, -2, 2, -2, -3, -2, -2, -5, 5, -3, 3, -5, 2, 3, 4, 3, -3, 1, -1, -2, 2, -4, 4, 5, -5, 3, -3, 0, -2, -2, -1, 3, -2, 5, -1, -2, 0, -2, -1, 3, -2, 17, -1, -2, 2, -4, -5, -2, -1, 3, 5, 4, -2, -7, 0, 7, -7, 7, 3, -1, -2, -2, -3, 0, -2, -3, 3, 2, 2, 1, -5, -3, 0, -2, 0, 15, -1, -4, -5, -2, -1, 3, 5, 4, -2, -7, 0, 7, -7, 7, 2, 1, -1, -2, -3, 1, 2, -2, -3, -2, 2, 3, 2, 2, -4, 0, 5, -10, 2, 3, 2, 2, -4, -5, -3], "pitchproximity": [null, null, 5, 3, 3, 5, 2, 3, 4, 3, 3, 1, 1, 2, 2, 4, 4, 0, 3, 10, 1, 2, 2, 3, 0, 2, 2, 2, 3, 2, 2, 5, 5, 3, 3, 5, 2, 3, 4, 3, 3, 1, 1, 2, 2, 4, 4, 5, 5, 3, 3, 0, 2, 2, 1, 3, 2, 5, 1, 2, 0, 2, 1, 3, 2, null, 1, 2, 2, 4, 5, 2, 1, 3, 5, 4, 2, 7, 0, 7, 7, 7, 3, 1, 2, 2, 3, 0, 2, 3, 3, 2, 2, 1, 5, 3, 0, 2, 0, null, 1, 4, 5, 2, 1, 3, 5, 4, 2, 7, 0, 7, 7, 7, 2, 1, 1, 2, 3, 1, 2, 2, 3, 2, 2, 3, 2, 2, 4, 0, 5, 10, 2, 3, 2, 2, 4, 5, 3], "pitchreversal": [null, null, 1.5, 1.5, 1.5, 1.5, 0, 0, 0, 0, 1.5, 1.5, 1.5, 0, 1.5, 1.5, 1.5, 0, 0, 0, 1, 0, 0, 0, 0, 0, 1.5, 1.5, 0, 0, 0, 0, 1.5, 1.5, 1.5, 1.5, 0, 0, 0, 0, 1.5, 1.5, 1.5, 0, 1.5, 1.5, 1.5, 0, 1.5, 1.5, 1.5, 0, 0, 0, 0, 1.5, 1.5, 0, 0, 0, 0, 0, 0, 1.5, 1.5, null, null, 0, 1.5, 1.5, 0, 0, 0, 1.5, 0, 0, 1.5, 0, 1, 0, 2.5, 2.5, -1, 1.5, 0, 0, 0, 0, 0, 0, 1.5, 0, 0, 0, 0, 0, 0, 0, 0, null, null, 0, 0, 0, 0, 1.5, 0, 0, 1.5, 0, 1, 0, 2.5, 2.5, -1, 0, 1.5, 0, 0, 1.5, 0, 1.5, 0, 0, 1.5, 0, 0, 0, 1.5, 0, 0, 0, 1, 0, 0, 0, 1.5, 0, 0], "nextisrest": [false, false, false, false, false, false, false, false, false, false, false, false, false, false, false, false, false, false, false, false, false, false, false, false, false, false, false, false, false, false, false, false, false, false, false, false, false, false, false, false, false, false, false, false, false, false, false, false, false, false, false, false, false, false, false, false, false, false, false, false, false, false, false, false, false, false, false, false, false, false, false, false, false, false, false, false, false, false, false, false, false, false, false, false, false, false, false, false, false, false, false, false, false, false, false, false, false, false, false, false, false, false, false, false, false, false, false, false, false, false, false, false, false, false, false, false, false, false, false, false, false, false, false, false, false, false, false, false, false, false, false, false, false, false, false, false, false, false, null], "restduration_frac": [null, null, null, null, null, null, null, null, null, null, null, null, null, null, null, null, null, null, null, null, null, null, null, null, null, null, null, null, null, null, null, null, null, null, null, null, null, null, null, null, null, null, null, null, null, null, null, null, null, null, null, null, null, null, null, null, null, null, null, null, null, null, null, null, null, null, null, null, null, null, null, null, null, null, null, null, null, null, null, null, null, null, null, null, null, null, null, null, null, null, null, null, null, null, null, null, null, null, null, null, null, null, null, null, null, null, null, null, null, null, null, null, null, null, null, null, null, null, null, null, null, null, null, null, null, null, null, null, null, null, null, null, null, null, null, null, null, null, null], "duration": [1.0, 0.5, 0.5, 0.5, 0.5, 0.5, 0.5, 0.5, 0.5, 0.5, 0.5, 0.5, 0.5, 0.5, 0.5, 0.5, 0.5, 1.0, 0.5, 0.5, 0.5, 0.5, 0.5, 0.5, 0.5, 0.5, 0.5, 0.5, 0.5, 0.5, 1.0, 0.5, 0.5, 0.5, 0.5, 0.5, 0.5, 0.5, 0.5, 0.5, 0.5, 0.5, 0.5, 0.5, 0.5, 0.5, 0.5, 0.5, 0.5, 0.5, 0.5, 1.0, 0.5, 0.5, 0.5, 0.5, 0.5, 0.25, 0.25, 0.5, 0.5, 0.5, 0.5, 0.5, 1.0, 0.25, 0.25, 0.5, 0.5, 0.5, 0.5, 0.5, 0.5, 0.5, 0.5, 0.5, 0.5, 0.5, 1.0, 0.5, 0.5, 0.5, 0.5, 0.5, 0.5, 0.5, 0.5, 0.5, 0.5, 0.5, 0.5, 0.25, 0.25, 0.5, 0.5, 0.5, 0.5, 0.5, 0.5, 0.5, 0.5, 0.5, 0.5, 0.5, 0.5, 0.5, 0.5, 0.5, 0.5, 0.5, 1.0, 0.5, 0.5, 0.5, 0.5, 0.5, 0.5, 0.5, 0.5, 0.5, 0.5, 0.5, 0.5, 0.5, 0.5, 0.5, 0.5, 0.5, 0.5, 0.5, 0.5, 0.5, 0.5, 0.5, 0.5, 0.5, 0.5, 0.5, 0.5], "duration_frac": ["1", "1/2", "1/2", "1/2", "1/2", "1/2", "1/2", "1/2", "1/2", "1/2", "1/2", "1/2", "1/2", "1/2", "1/2", "1/2", "1/2", "1", "1/2", "1/2", "1/2", "1/2", "1/2", "1/2", "1/2", "1/2", "1/2", "1/2", "1/2", "1/2", "1", "1/2", "1/2", "1/2", "1/2", "1/2", "1/2", "1/2", "1/2", "1/2", "1/2", "1/2", "1/2", "1/2", "1/2", "1/2", "1/2", "1/2", "1/2", "1/2", "1/2", "1", "1/2", "1/2", "1/2", "1/2", "1/2", "1/4", "1/4", "1/2", "1/2", "1/2", "1/2", "1/2", "1", "1/4", "1/4", "1/2", "1/2", "1/2", "1/2", "1/2", "1/2", "1/2", "1/2", "1/2", "1/2", "1/2", "1", "1/2", "1/2", "1/2", "1/2", "1/2", "1/2", "1/2", "1/2", "1/2", "1/2", "1/2", "1/2", "1/4", "1/4", "1/2", "1/2", "1/2", "1/2", "1/2", "1/2", "1/2", "1/2", "1/2", "1/2", "1/2", "1/2", "1/2", "1/2", "1/2", "1/2", "1/2", "1", "1/2", "1/2", "1/2", "1/2", "1/2", "1/2", "1/2", "1/2", "1/2", "1/2", "1/2", "1/2", "1/2", "1/2", "1/2", "1/2", "1/2", "1/2", "1/2", "1/2", "1/2", "1/2", "1/2", "1/2", "1/2", "1/2", "1/2", "1/2"], "duration_fullname": ["Quarter", "Eighth", "Eighth", "Eighth", "Eighth", "Eighth", "Eighth", "Eighth", "Eighth", "Eighth", "Eighth", "Eighth", "Eighth", "Eighth", "Eighth", "Eighth", "Eighth", "Quarter", "Eighth", "Eighth", "Eighth", "Eighth", "Eighth", "Eighth", "Eighth", "Eighth", "Eighth", "Eighth", "Eighth", "Eighth", "Quarter", "Eighth", "Eighth", "Eighth", "Eighth", "Eighth", "Eighth", "Eighth", "Eighth", "Eighth", "Eighth", "Eighth", "Eighth", "Eighth", "Eighth", "Eighth", "Eighth", "Eighth", "Eighth", "Eighth", "Eighth", "Quarter", "Eighth", "Eighth", "Eighth", "Eighth", "Eighth", "16th", "16th", "Eighth", "Eighth", "Eighth", "Eighth", "Eighth", "Quarter", "16th", "16th", "Eighth", "Eighth", "Eighth", "Eighth", "Eighth", "Eighth", "Eighth", "Eighth", "Eighth", "Eighth", "Eighth", "Quarter", "Eighth", "Eighth", "Eighth", "Eighth", "Eighth", "Eighth", "Eighth", "Eighth", "Eighth", "Eighth", "Eighth", "Eighth", "16th", "16th", "Eighth", "Eighth", "Eighth", "Eighth", "Eighth", "Eighth", "Eighth", "Eighth", "Eighth", "Eighth", "Eighth", "Eighth", "Eighth", "Eighth", "Eighth", "Eighth", "Eighth", "Quarter", "Eighth", "Eighth", "Eighth", "Eighth", "Eighth", "Eighth", "Eighth", "Eighth", "Eighth", "Eighth", "Eighth", "Eighth", "Eighth", "Eighth", "Eighth", "Eighth", "Eighth", "Eighth", "Eighth", "Eighth", "Eighth", "Eighth", "Eighth", "Eighth", "Eighth", "Eighth", "Eighth", "Eighth"], "durationcontour": [null, "-", "=", "=", "=", "=", "=", "=", "=", "=", "=", "=", "=", "=", "=", "=", "=", "+", "-", "=", "=", "=", "=", "=", "=", "=", "=", "=", "=", "=", "+", "-", "=", "=", "=", "=", "=", "=", "=", "=", "=", "=", "=", "=", "=", "=", "=", "=", "=", "=", "=", "+", "-", "=", "=", "=", "=", "-", "=", "+", "=", "=", "=", "=", "+", "-", "=", "+", "=", "=", "=", "=", "=", "=", "=", "=", "=", "=", "+", "-", "=", "=", "=", "=", "=", "=", "=", "=", "=", "=", "=", "-", "=", "+", "=", "=", "=", "=", "=", "=", "=", "=", "=", "=", "=", "=", "=", "=", "=", "=", "+", "-", "=", "=", "=", "=", "=", "=", "=", "=", "=", "=", "=", "=", "=", "=", "=", "=", "=", "=", "=", "=", "=", "=", "=", "=", "=", "=", "="], "onsettick": [0, 4, 6, 8, 10, 12, 14, 16, 18, 20, 22, 24, 26, 28, 30, 32, 34, 36, 40, 42, 44, 46, 48, 50, 52, 54, 56, 58, 60, 62, 64, 68, 70, 72, 74, 76, 78, 80, 82, 84, 86, 88, 90, 92, 94, 96, 98, 100, 102, 104, 106, 108, 112, 114, 116, 118, 120, 122, 123, 124, 126, 128, 130, 132, 134, 138, 139, 140, 142, 144, 146, 148, 150, 152, 154, 156, 158, 160, 162, 166, 168, 170, 172, 174, 176, 178, 180, 182, 184, 186, 188, 190, 191, 192, 194, 196, 198, 200, 202, 204, 206, 208, 210, 212, 214, 216, 218, 220, 222, 224, 226, 230, 232, 234, 236, 238, 240, 242, 244, 246, 248, 250, 252, 254, 256, 258, 260, 262, 264, 266, 268, 270, 272, 274, 276, 278, 280, 282, 284], "beatfraction": ["1", "1/2", "1/2", "1/2", "1/2", "1/2", "1/2", "1/2", "1/2", "1/2", "1/2", "1/2", "1/2", "1/2", "1/2", "1/2", "1/2", "1", "1/2", "1/2", "1/2", "1/2", "1/2", "1/2", "1/2", "1/2", "1/2", "1/2", "1/2", "1/2", "1", "1/2", "1/2", "1/2", "1/2", "1/2", "1/2", "1/2", "1/2", "1/2", "1/2", "1/2", "1/2", "1/2", "1/2", "1/2", "1/2", "1/2", "1/2", "1/2", "1/2", "1", "1/2", "1/2", "1/2", "1/2", "1/2", "1/4", "1/4", "1/2", "1/2", "1/2", "1/2", "1/2", "1", "1/4", "1/4", "1/2", "1/2", "1/2", "1/2", "1/2", "1/2", "1/2", "1/2", "1/2", "1/2", "1/2", "1", "1/2", "1/2", "1/2", "1/2", "1/2", "1/2", "1/2", "1/2", "1/2", "1/2", "1/2", "1/2", "1/4", "1/4", "1/2", "1/2", "1/2", "1/2", "1/2", "1/2", "1/2", "1/2", "1/2", "1/2", "1/2", "1/2", "1/2", "1/2", "1/2", "1/2", "1/2", "1", "1/2", "1/2", "1/2", "1/2", "1/2", "1/2", "1/2", "1/2", "1/2", "1/2", "1/2", "1/2", "1/2", "1/2", "1/2", "1/2", "1/2", "1/2", "1/2", "1/2", "1/2", "1/2", "1/2", "1/2", "1/2", "1/2", "1/2", "1/2"], "phrasepos": [0.0, 0.06451612903225806, 0.0967741935483871, 0.12903225806451613, 0.16129032258064516, 0.1935483870967742, 0.22580645161290322, 0.25806451612903225, 0.2903225806451613, 0.3225806451612903, 0.3548387096774194, 0.3870967741935484, 0.41935483870967744, 0.45161290322580644, 0.4838709677419355, 0.5161290322580645, 0.5483870967741935, 0.5806451612903226, 0.6451612903225806, 0.6774193548387096, 0.7096774193548387, 0.7419354838709677, 0.7741935483870968, 0.8064516129032258, 0.8387096774193549, 0.8709677419354839, 0.9032258064516129, 0.9354838709677419, 0.967741935483871, 1.0, 0.0, 0.05263157894736842, 0.07894736842105263, 0.10526315789473684, 0.13157894736842105, 0.15789473684210525, 0.18421052631578946, 0.21052631578947367, 0.23684210526315788, 0.2631578947368421, 0.2894736842105263, 0.3157894736842105, 0.34210526315789475, 0.3684210526315789, 0.39473684210526316, 0.42105263157894735, 0.4473684210526316, 0.47368421052631576, 0.5, 0.5263157894736842, 0.5526315789473685, 0.5789473684210527, 0.631578947368421, 0.6578947368421053, 0.6842105263157895, 0.7105263157894737, 0.7368421052631579, 0.7631578947368421, 0.7763157894736842, 0.7894736842105263, 0.8157894736842105, 0.8421052631578947, 0.868421052631579, 0.8947368421052632, 0.9210526315789473, 0.9736842105263158, 0.9868421052631579, 1.0, 0.0, 0.03225806451612903, 0.06451612903225806, 0.0967741935483871, 0.12903225806451613, 0.16129032258064516, 0.1935483870967742, 0.22580645161290322, 0.25806451612903225, 0.2903225806451613, 0.3225806451612903, 0.3870967741935484, 0.41935483870967744, 0.45161290322580644, 0.4838709677419355, 0.5161290322580645, 0.5483870967741935, 0.5806451612903226, 0.6129032258064516, 0.6451612903225806, 0.6774193548387096, 0.7096774193548387, 0.7419354838709677, 0.7741935483870968, 0.7903225806451613, 0.8064516129032258, 0.8387096774193549, 0.8709677419354839, 0.9032258064516129, 0.9354838709677419, 0.967741935483871, 1.0, 0.0, 0.02564102564102564, 0.05128205128205128, 0.07692307692307693, 0.10256410256410256, 0.1282051282051282, 0.15384615384615385, 0.1794871794871795, 0.20512820512820512, 0.23076923076923078, 0.2564102564102564, 0.3076923076923077, 0.3333333333333333, 0.358974358974359, 0.38461538461538464, 0.41025641025641024, 0.4358974358974359, 0.46153846153846156, 0.48717948717948717, 0.5128205128205128, 0.5384615384615384, 0.5641025641025641, 0.5897435897435898, 0.6153846153846154, 0.6410256410256411, 0.6666666666666666, 0.6923076923076923, 0.717948717948718, 0.7435897435897436, 0.7692307692307693, 0.7948717948717948, 0.8205128205128205, 0.8461538461538461, 0.8717948717948718, 0.8974358974358975, 0.9230769230769231, 0.9487179487179487, 0.9743589743589743, 1.0], "phrase_ix": [0, 0, 0, 0, 0, 0, 0, 0, 0, 0, 0, 0, 0, 0, 0, 0, 0, 0, 0, 0, 0, 0, 0, 0, 0, 0, 0, 0, 0, 0, 1, 1, 1, 1, 1, 1, 1, 1, 1, 1, 1, 1, 1, 1, 1, 1, 1, 1, 1, 1, 1, 1, 1, 1, 1, 1, 1, 1, 1, 1, 1, 1, 1, 1, 1, 1, 1, 1, 2, 2, 2, 2, 2, 2, 2, 2, 2, 2, 2, 2, 2, 2, 2, 2, 2, 2, 2, 2, 2, 2, 2, 2, 2, 2, 2, 2, 2, 2, 2, 2, 3, 3, 3, 3, 3, 3, 3, 3, 3, 3, 3, 3, 3, 3, 3, 3, 3, 3, 3, 3, 3, 3, 3, 3, 3, 3, 3, 3, 3, 3, 3, 3, 3, 3, 3, 3, 3, 3, 3], "phrase_end": [false, false, false, false, false, false, false, false, false, false, false, false, false, false, false, false, false, false, false, false, false, false, false, false, false, false, false, false, false, true, false, false, false, false, false, false, false, false, false, false, false, false, false, false, false, false, false, false, false, false, false, false, false, false, false, false, false, false, false, false, false, false, false, false, false, false, false, true, false, false, false, false, false, false, false, false, false, false, false, false, false, false, false, false, false, false, false, false, false, false, false, false, false, false, false, false, false, false, false, true, false, false, false, false, false, false, false, false, false, false, false, false, false, false, false, false, false, false, false, false, false, false, false, false, false, false, false, false, false, false, false, false, false, false, false, false, false, false, true], "songpos": [0.0, 0.014084507042253521, 0.02112676056338028, 0.028169014084507043, 0.035211267605633804, 0.04225352112676056, 0.04929577464788732, 0.056338028169014086, 0.06338028169014084, 0.07042253521126761, 0.07746478873239436, 0.08450704225352113, 0.09154929577464789, 0.09859154929577464, 0.1056338028169014, 0.11267605633802817, 0.11971830985915492, 0.1267605633802817, 0.14084507042253522, 0.14788732394366197, 0.15492957746478872, 0.1619718309859155, 0.16901408450704225, 0.176056338028169, 0.18309859154929578, 0.19014084507042253, 0.19718309859154928, 0.20422535211267606, 0.2112676056338028, 0.21830985915492956, 0.22535211267605634, 0.23943661971830985, 0.24647887323943662, 0.2535211267605634, 0.2605633802816901, 0.2676056338028169, 0.2746478873239437, 0.28169014084507044, 0.2887323943661972, 0.29577464788732394, 0.3028169014084507, 0.30985915492957744, 0.31690140845070425, 0.323943661971831, 0.33098591549295775, 0.3380281690140845, 0.34507042253521125, 0.352112676056338, 0.3591549295774648, 0.36619718309859156, 0.3732394366197183, 0.38028169014084506, 0.39436619718309857, 0.4014084507042254, 0.4084507042253521, 0.4154929577464789, 0.4225352112676056, 0.4295774647887324, 0.43309859154929575, 0.43661971830985913, 0.44366197183098594, 0.4507042253521127, 0.45774647887323944, 0.4647887323943662, 0.47183098591549294, 0.4859154929577465, 0.4894366197183099, 0.49295774647887325, 0.5, 0.5070422535211268, 0.5140845070422535, 0.5211267605633803, 0.528169014084507, 0.5352112676056338, 0.5422535211267606, 0.5492957746478874, 0.5563380281690141, 0.5633802816901409, 0.5704225352112676, 0.5845070422535211, 0.5915492957746479, 0.5985915492957746, 0.6056338028169014, 0.6126760563380281, 0.6197183098591549, 0.6267605633802817, 0.6338028169014085, 0.6408450704225352, 0.647887323943662, 0.6549295774647887, 0.6619718309859155, 0.6690140845070423, 0.6725352112676056, 0.676056338028169, 0.6830985915492958, 0.6901408450704225, 0.6971830985915493, 0.704225352112676, 0.7112676056338029, 0.7183098591549296, 0.7253521126760564, 0.7323943661971831, 0.7394366197183099, 0.7464788732394366, 0.7535211267605634, 0.7605633802816901, 0.7676056338028169, 0.7746478873239436, 0.7816901408450704, 0.7887323943661971, 0.795774647887324, 0.8098591549295775, 0.8169014084507042, 0.823943661971831, 0.8309859154929577, 0.8380281690140845, 0.8450704225352113, 0.852112676056338, 0.8591549295774648, 0.8661971830985915, 0.8732394366197183, 0.8802816901408451, 0.8873239436619719, 0.8943661971830986, 0.9014084507042254, 0.9084507042253521, 0.9154929577464789, 0.9225352112676056, 0.9295774647887324, 0.9366197183098591, 0.9436619718309859, 0.9507042253521126, 0.9577464788732394, 0.9647887323943662, 0.971830985915493, 0.9788732394366197, 0.9859154929577465, 0.9929577464788732, 1.0], "beatinsong": ["0", "1", "3/2", "2", "5/2", "3", "7/2", "4", "9/2", "5", "11/2", "6", "13/2", "7", "15/2", "8", "17/2", "9", "10", "21/2", "11", "23/2", "12", "25/2", "13", "27/2", "14", "29/2", "15", "31/2", "16", "17", "35/2", "18", "37/2", "19", "39/2", "20", "41/2", "21", "43/2", "22", "45/2", "23", "47/2", "24", "49/2", "25", "51/2", "26", "53/2", "27", "28", "57/2", "29", "59/2", "30", "61/2", "123/4", "31", "63/2", "32", "65/2", "33", "67/2", "69/2", "139/4", "35", "71/2", "36", "73/2", "37", "75/2", "38", "77/2", "39", "79/2", "40", "81/2", "83/2", "42", "85/2", "43", "87/2", "44", "89/2", "45", "91/2", "46", "93/2", "47", "95/2", "191/4", "48", "97/2", "49", "99/2", "50", "101/2", "51", "103/2", "52", "105/2", "53", "107/2", "54", "109/2", "55", "111/2", "56", "113/2", "115/2", "58", "117/2", "59", "119/2", "60", "121/2", "61", "123/2", "62", "125/2", "63", "127/2", "64", "129/2", "65", "131/2", "66", "133/2", "67", "135/2", "68", "137/2", "69", "139/2", "70", "141/2", "71"], "beatinphrase": ["0", "1", "3/2", "2", "5/2", "3", "7/2", "4", "9/2", "5", "11/2", "6", "13/2", "7", "15/2", "8", "17/2", "9", "10", "21/2", "11", "23/2", "12", "25/2", "13", "27/2", "14", "29/2", "15", "31/2", "0", "1", "3/2", "2", "5/2", "3", "7/2", "4", "9/2", "5", "11/2", "6", "13/2", "7", "15/2", "8", "17/2", "9", "19/2", "10", "21/2", "11", "12", "25/2", "13", "27/2", "14", "29/2", "59/4", "15", "31/2", "16", "33/2", "17", "35/2", "37/2", "75/4", "19", "0", "1/2", "1", "3/2", "2", "5/2", "3", "7/2", "4", "9/2", "5", "6", "13/2", "7", "15/2", "8", "17/2", "9", "19/2", "10", "21/2", "11", "23/2", "12", "49/4", "25/2", "13", "27/2", "14", "29/2", "15", "31/2", "0", "1/2", "1", "3/2", "2", "5/2", "3", "7/2", "4", "9/2", "5", "6", "13/2", "7", "15/2", "8", "17/2", "9", "19/2", "10", "21/2", "11", "23/2", "12", "25/2", "13", "27/2", "14", "29/2", "15", "31/2", "16", "33/2", "17", "35/2", "18", "37/2", "19", "39/2"], "beatinphrase_end": ["-12", "-11", "-21/2", "-10", "-19/2", "-9", "-17/2", "-8", "-15/2", "-7", "-13/2", "-6", "-11/2", "-5", "-9/2", "-4", "-7/2", "-3", "-2", "-3/2", "-1", "-1/2", "0", "1/2", "1", "3/2", "2", "5/2", "3", "7/2", "-31/2", "-29/2", "-14", "-27/2", "-13", "-25/2", "-12", "-23/2", "-11", "-21/2", "-10", "-19/2", "-9", "-17/2", "-8", "-15/2", "-7", "-13/2", "-6", "-11/2", "-5", "-9/2", "-7/2", "-3", "-5/2", "-2", "-3/2", "-1", "-3/4", "-1/2", "0", "1/2", "1", "3/2", "2", "3", "13/4", "7/2", "-12", "-23/2", "-11", "-21/2", "-10", "-19/2", "-9", "-17/2", "-8", "-15/2", "-7", "-6", "-11/2", "-5", "-9/2", "-4", "-7/2", "-3", "-5/2", "-2", "-3/2", "-1", "-1/2", "0", "1/4", "1/2", "1", "3/2", "2", "5/2", "3", "7/2", "-16", "-31/2", "-15", "-29/2", "-14", "-27/2", "-13", "-25/2", "-12", "-23/2", "-11", "-10", "-19/2", "-9", "-17/2", "-8", "-15/2", "-7", "-13/2", "-6", "-11/2", "-5", "-9/2", "-4", "-7/2", "-3", "-5/2", "-2", "-3/2", "-1", "-1/2", "0", "1/2", "1", "3/2", "2", "5/2", "3", "7/2"], "IOI_frac": ["1", "1/2", "1/2", "1/2", "1/2", "1/2", "1/2", "1/2", "1/2", "1/2", "1/2", "1/2", "1/2", "1/2", "1/2", "1/2", "1/2", "1", "1/2", "1/2", "1/2", "1/2", "1/2", "1/2", "1/2", "1/2", "1/2", "1/2", "1/2", "1/2", "1", "1/2", "1/2", "1/2", "1/2", "1/2", "1/2", "1/2", "1/2", "1/2", "1/2", "1/2", "1/2", "1/2", "1/2", "1/2", "1/2", "1/2", "1/2", "1/2", "1/2", "1", "1/2", "1/2", "1/2", "1/2", "1/2", "1/4", "1/4", "1/2", "1/2", "1/2", "1/2", "1/2", "1", "1/4", "1/4", "1/2", "1/2", "1/2", "1/2", "1/2", "1/2", "1/2", "1/2", "1/2", "1/2", "1/2", "1", "1/2", "1/2", "1/2", "1/2", "1/2", "1/2", "1/2", "1/2", "1/2", "1/2", "1/2", "1/2", "1/4", "1/4", "1/2", "1/2", "1/2", "1/2", "1/2", "1/2", "1/2", "1/2", "1/2", "1/2", "1/2", "1/2", "1/2", "1/2", "1/2", "1/2", "1/2", "1", "1/2", "1/2", "1/2", "1/2", "1/2", "1/2", "1/2", "1/2", "1/2", "1/2", "1/2", "1/2", "1/2", "1/2", "1/2", "1/2", "1/2", "1/2", "1/2", "1/2", "1/2", "1/2", "1/2", "1/2", "1/2", "1/2", "1/2", null], "IOI": [1.0, 0.5, 0.5, 0.5, 0.5, 0.5, 0.5, 0.5, 0.5, 0.5, 0.5, 0.5, 0.5, 0.5, 0.5, 0.5, 0.5, 1.0, 0.5, 0.5, 0.5, 0.5, 0.5, 0.5, 0.5, 0.5, 0.5, 0.5, 0.5, 0.5, 1.0, 0.5, 0.5, 0.5, 0.5, 0.5, 0.5, 0.5, 0.5, 0.5, 0.5, 0.5, 0.5, 0.5, 0.5, 0.5, 0.5, 0.5, 0.5, 0.5, 0.5, 1.0, 0.5, 0.5, 0.5, 0.5, 0.5, 0.25, 0.25, 0.5, 0.5, 0.5, 0.5, 0.5, 1.0, 0.25, 0.25, 0.5, 0.5, 0.5, 0.5, 0.5, 0.5, 0.5, 0.5, 0.5, 0.5, 0.5, 1.0, 0.5, 0.5, 0.5, 0.5, 0.5, 0.5, 0.5, 0.5, 0.5, 0.5, 0.5, 0.5, 0.25, 0.25, 0.5, 0.5, 0.5, 0.5, 0.5, 0.5, 0.5, 0.5, 0.5, 0.5, 0.5, 0.5, 0.5, 0.5, 0.5, 0.5, 0.5, 1.0, 0.5, 0.5, 0.5, 0.5, 0.5, 0.5, 0.5, 0.5, 0.5, 0.5, 0.5, 0.5, 0.5, 0.5, 0.5, 0.5, 0.5, 0.5, 0.5, 0.5, 0.5, 0.5, 0.5, 0.5, 0.5, 0.5, 0.5, null], "IOR_frac": [null, "1/2", "1", "1", "1", "1", "1", "1", "1", "1", "1", "1", "1", "1", "1", "1", "1", "2", "1/2", "1", "1", "1", "1", "1", "1", "1", "1", "1", "1", "1", "2", "1/2", "1", "1", "1", "1", "1", "1", "1", "1", "1", "1", "1", "1", "1", "1", "1", "1", "1", "1", "1", "2", "1/2", "1", "1", "1", "1", "1/2", "1", "2", "1", "1", "1", "1", "2", "1/4", "1", "2", "1", "1", "1", "1", "1", "1", "1", "1", "1", "1", "2", "1/2", "1", "1", "1", "1", "1", "1", "1", "1", "1", "1", "1", "1/2", "1", "2", "1", "1", "1", "1", "1", "1", "1", "1", "1", "1", "1", "1", "1", "1", "1", "1", "2", "1/2", "1", "1", "1", "1", "1", "1", "1", "1", "1", "1", "1", "1", "1", "1", "1", "1", "1", "1", "1", "1", "1", "1", "1", "1", "1", "1", null], "IOR": [null, 0.5, 1.0, 1.0, 1.0, 1.0, 1.0, 1.0, 1.0, 1.0, 1.0, 1.0, 1.0, 1.0, 1.0, 1.0, 1.0, 2.0, 0.5, 1.0, 1.0, 1.0, 1.0, 1.0, 1.0, 1.0, 1.0, 1.0, 1.0, 1.0, 2.0, 0.5, 1.0, 1.0, 1.0, 1.0, 1.0, 1.0, 1.0, 1.0, 1.0, 1.0, 1.0, 1.0, 1.0, 1.0, 1.0, 1.0, 1.0, 1.0, 1.0, 2.0, 0.5, 1.0, 1.0, 1.0, 1.0, 0.5, 1.0, 2.0, 1.0, 1.0, 1.0, 1.0, 2.0, 0.25, 1.0, 2.0, 1.0, 1.0, 1.0, 1.0, 1.0, 1.0, 1.0, 1.0, 1.0, 1.0, 2.0, 0.5, 1.0, 1.0, 1.0, 1.0, 1.0, 1.0, 1.0, 1.0, 1.0, 1.0, 1.0, 0.5, 1.0, 2.0, 1.0, 1.0, 1.0, 1.0, 1.0, 1.0, 1.0, 1.0, 1.0, 1.0, 1.0, 1.0, 1.0, 1.0, 1.0, 1.0, 2.0, 0.5, 1.0, 1.0, 1.0, 1.0, 1.0, 1.0, 1.0, 1.0, 1.0, 1.0, 1.0, 1.0, 1.0, 1.0, 1.0, 1.0, 1.0, 1.0, 1.0, 1.0, 1.0, 1.0, 1.0, 1.0, 1.0, 1.0, null], "imacontour": [null, "+", "-", "+", "-", "+", "-", "+", "-", "+", "-", "+", "-", "+", "-", "+", "-", "+", "-", "-", "+", "-", "+", "-", "+", "-", "+", "+", "+", "-", "+", "+", "-", "+", "-", "+", "-", "+", "+", "+", "-", "+", "+", "+", "-", "+", "-", "+", "-", "+", "+", "+", "-", "+", "-", "+", "-", "+", "-", "+", "+", "-", "+", "-", "-", "+", "-", "+", "+", "-", "+", "-", "+", "-", "+", "-", "+", "-", "+", "-", "-", "+", "-", "+", "-", "+", "-", "+", "-", "+", "-", "+", "-", "+", "+", "-", "+", "-", "+", "-", "+", "-", "+", "-", "+", "-", "+", "-", "+", "-", "+", "-", "-", "+", "-", "+", "-", "+", "-", "+", "-", "+", "-", "+", "-", "+", "-", "+", "-", "+", "-", "+", "-", "+", "-", "+", "-", "+", "-"], "pitch": ["D4", "A3", "D4", "B3", "D4", "A3", "B3", "D4", "F#4", "A4", "F#4", "G4", "F#4", "E4", "F#4", "D4", "F#4", "F#4", "A4", "G5", "F#5", "E5", "D5", "B4", "B4", "A4", "B4", "A4", "F#4", "E4", "D4", "A3", "D4", "B3", "D4", "A3", "B3", "D4", "F#4", "A4", "F#4", "G4", "F#4", "E4", "F#4", "D4", "F#4", "B4", "F#4", "A4", "F#4", "F#4", "E4", "D4", "C#4", "E4", "D4", "G4", "F#4", "E4", "E4", "D4", "C#4", "E4", "D4", "G5", "F#5", "E5", "F#5", "D5", "A4", "G4", "F#4", "A4", "D5", "F#5", "E5", "A4", "A4", "E5", "A4", "E5", "G5", "F#5", "E5", "D5", "B4", "B4", "A4", "F#4", "A4", "B4", "C#5", "D5", "A4", "F#4", "F#4", "E4", "E4", "G5", "F#5", "D5", "A4", "G4", "F#4", "A4", "D5", "F#5", "E5", "A4", "A4", "E5", "A4", "E5", "F#5", "G5", "F#5", "E5", "C#5", "D5", "E5", "D5", "B4", "A4", "B4", "D5", "E5", "F#5", "D5", "D5", "G5", "A4", "B4", "D5", "E5", "F#5", "D5", "A4", "F#4"], "contour3": [null, "-", "+", "-", "+", "-", "+", "+", "+", "+", "-", "+", "-", "-", "+", "-", "+", "=", "+", "+", "-", "-", "-", "-", "=", "-", "+", "-", "-", "-", "-", "-", "+", "-", "+", "-", "+", "+", "+", "+", "-", "+", "-", "-", "+", "-", "+", "+", "-", "+", "-", "=", "-", "-", "-", "+", "-", "+", "-", "-", "=", "-", "-", "+", "-", "+", "-", "-", "+", "-", "-", "-", "-", "+", "+", "+", "-", "-", "=", "+", "-", "+", "+", "-", "-", "-", "-", "=", "-", "-", "+", "+", "+", "+", "-", "-", "=", "-", "=", "+", "-", "-", "-", "-", "-", "+", "+", "+", "-", "-", "=", "+", "-", "+", "+", "+", "-", "-", "-", "+", "+", "-", "-", "-", "+", "+", "+", "+", "-", "=", "+", "-", "+", "+", "+", "+", "-", "-", "-"], "contour5": [null, "--", "++", "--", "++", "--", "+", "++", "++", "++", "--", "+", "-", "-", "+", "--", "++", "=", "++", "++", "-", "-", "-", "--", "=", "-", "+", "-", "--", "-", "-", "--", "++", "--", "++", "--", "+", "++", "++", "++", "--", "+", "-", "-", "+", "--", "++", "++", "--", "++", "--", "=", "-", "-", "-", "++", "-", "++", "-", "-", "=", "-", "-", "++", "-", "++", "-", "-", "+", "--", "--", "-", "-", "++", "++", "++", "-", "--", "=", "++", "--", "++", "++", "-", "-", "-", "--", "=", "-", "--", "++", "+", "+", "+", "--", "--", "=", "-", "=", "++", "-", "--", "--", "-", "-", "++", "++", "++", "-", "--", "=", "++", "--", "++", "+", "+", "-", "-", "--", "+", "+", "-", "--", "-", "+", "++", "+", "+", "--", "=", "++", "--", "+", "++", "+", "+", "--", "--", "--"], "beatstrength": [1.0, 0.25, 0.125, 0.5, 0.125, 0.25, 0.125, 1.0, 0.125, 0.25, 0.125, 0.5, 0.125, 0.25, 0.125, 1.0, 0.125, 0.25, 0.5, 0.125, 0.25, 0.125, 1.0, 0.125, 0.25, 0.125, 0.5, 0.125, 0.25, 0.125, 1.0, 0.25, 0.125, 0.5, 0.125, 0.25, 0.125, 1.0, 0.125, 0.25, 0.125, 0.5, 0.125, 0.25, 0.125, 1.0, 0.125, 0.25, 0.125, 0.5, 0.125, 0.25, 1.0, 0.125, 0.25, 0.125, 0.5, 0.125, 0.0625, 0.25, 1.0, 0.125, 0.25, 0.125, 0.5, 0.25, 0.0625, 0.125, 1.0, 0.125, 0.25, 0.125, 0.5, 0.125, 0.25, 0.125, 1.0, 0.125, 0.25, 0.5, 0.125, 0.25, 0.125, 1.0, 0.125, 0.25, 0.125, 0.5, 0.125, 0.25, 0.125, 1.0, 0.0625, 0.125, 0.25, 0.125, 0.5, 0.125, 0.25, 0.125, 1.0, 0.125, 0.25, 0.125, 0.5, 0.125, 0.25, 0.125, 1.0, 0.125, 0.25, 0.5, 0.125, 0.25, 0.125, 1.0, 0.125, 0.25, 0.125, 0.5, 0.125, 0.25, 0.125, 1.0, 0.125, 0.25, 0.125, 0.5, 0.125, 0.25, 0.125, 1.0, 0.125, 0.25, 0.125, 0.5, 0.125, 0.25, 0.125], "beat_str": ["1", "2", "2", "3", "3", "4", "4", "1", "1", "2", "2", "3", "3", "4", "4", "1", "1", "2", "3", "3", "4", "4", "1", "1", "2", "2", "3", "3", "4", "4", "1", "2", "2", "3", "3", "4", "4", "1", "1", "2", "2", "3", "3", "4", "4", "1", "1", "2", "2", "3", "3", "4", "1", "1", "2", "2", "3", "3", "3", "4", "1", "1", "2", "2", "3", "4", "4", "4", "1", "1", "2", "2", "3", "3", "4", "4", "1", "1", "2", "3", "3", "4", "4", "1", "1", "2", "2", "3", "3", "4", "4", "1", "1", "1", "2", "2", "3", "3", "4", "4", "1", "1", "2", "2", "3", "3", "4", "4", "1", "1", "2", "3", "3", "4", "4", "1", "1", "2", "2", "3", "3", "4", "4", "1", "1", "2", "2", "3", "3", "4", "4", "1", "1", "2", "2", "3", "3", "4", "4"], "beat_fraction_str": ["0", "0", "1/2", "0", "1/2", "0", "1/2", "0", "1/2", "0", "1/2", "0", "1/2", "0", "1/2", "0", "1/2", "0", "0", "1/2", "0", "1/2", "0", "1/2", "0", "1/2", "0", "1/2", "0", "1/2", "0", "0", "1/2", "0", "1/2", "0", "1/2", "0", "1/2", "0", "1/2", "0", "1/2", "0", "1/2", "0", "1/2", "0", "1/2", "0", "1/2", "0", "0", "1/2", "0", "1/2", "0", "1/2", "3/4", "0", "0", "1/2", "0", "1/2", "0", "0", "1/4", "1/2", "0", "1/2", "0", "1/2", "0", "1/2", "0", "1/2", "0", "1/2", "0", "0", "1/2", "0", "1/2", "0", "1/2", "0", "1/2", "0", "1/2", "0", "1/2", "0", "1/4", "1/2", "0", "1/2", "0", "1/2", "0", "1/2", "0", "1/2", "0", "1/2", "0", "1/2", "0", "1/2", "0", "1/2", "0", "0", "1/2", "0", "1/2", "0", "1/2", "0", "1/2", "0", "1/2", "0", "1/2", "0", "1/2", "0", "1/2", "0", "1/2", "0", "1/2", "0", "1/2", "0", "1/2", "0", "1/2", "0", "1/2"], "beat": [1.0, 2.0, 2.5, 3.0, 3.5, 4.0, 4.5, 1.0, 1.5, 2.0, 2.5, 3.0, 3.5, 4.0, 4.5, 1.0, 1.5, 2.0, 3.0, 3.5, 4.0, 4.5, 1.0, 1.5, 2.0, 2.5, 3.0, 3.5, 4.0, 4.5, 1.0, 2.0, 2.5, 3.0, 3.5, 4.0, 4.5, 1.0, 1.5, 2.0, 2.5, 3.0, 3.5, 4.0, 4.5, 1.0, 1.5, 2.0, 2.5, 3.0, 3.5, 4.0, 1.0, 1.5, 2.0, 2.5, 3.0, 3.5, 3.75, 4.0, 1.0, 1.5, 2.0, 2.5, 3.0, 4.0, 4.25, 4.5, 1.0, 1.5, 2.0, 2.5, 3.0, 3.5, 4.0, 4.5, 1.0, 1.5, 2.0, 3.0, 3.5, 4.0, 4.5, 1.0, 1.5, 2.0, 2.5, 3.0, 3.5, 4.0, 4.5, 1.0, 1.25, 1.5, 2.0, 2.5, 3.0, 3.5, 4.0, 4.5, 1.0, 1.5, 2.0, 2.5, 3.0, 3.5, 4.0, 4.5, 1.0, 1.5, 2.0, 3.0, 3.5, 4.0, 4.5, 1.0, 1.5, 2.0, 2.5, 3.0, 3.5, 4.0, 4.5, 1.0, 1.5, 2.0, 2.5, 3.0, 3.5, 4.0, 4.5, 1.0, 1.5, 2.0, 2.5, 3.0, 3.5, 4.0, 4.5], "timesignature": ["4/4", "4/4", "4/4", "4/4", "4/4", "4/4", "4/4", "4/4", "4/4", "4/4", "4/4", "4/4", "4/4", "4/4", "4/4", "4/4", "4/4", "4/4", "4/4", "4/4", "4/4", "4/4", "4/4", "4/4", "4/4", "4/4", "4/4", "4/4", "4/4", "4/4", "4/4", "4/4", "4/4", "4/4", "4/4", "4/4", "4/4", "4/4", "4/4", "4/4", "4/4", "4/4", "4/4", "4/4", "4/4", "4/4", "4/4", "4/4", "4/4", "4/4", "4/4", "4/4", "4/4", "4/4", "4/4", "4/4", "4/4", "4/4", "4/4", "4/4", "4/4", "4/4", "4/4", "4/4", "4/4", "4/4", "4/4", "4/4", "4/4", "4/4", "4/4", "4/4", "4/4", "4/4", "4/4", "4/4", "4/4", "4/4", "4/4", "4/4", "4/4", "4/4", "4/4", "4/4", "4/4", "4/4", "4/4", "4/4", "4/4", "4/4", "4/4", "4/4", "4/4", "4/4", "4/4", "4/4", "4/4", "4/4", "4/4", "4/4", "4/4", "4/4", "4/4", "4/4", "4/4", "4/4", "4/4", "4/4", "4/4", "4/4", "4/4", "4/4", "4/4", "4/4", "4/4", "4/4", "4/4", "4/4", "4/4", "4/4", "4/4", "4/4", "4/4", "4/4", "4/4", "4/4", "4/4", "4/4", "4/4", "4/4", "4/4", "4/4", "4/4", "4/4", "4/4", "4/4", "4/4", "4/4", "4/4"], "gpr2a_Frankland": [null, null, null, null, null, null, null, null, null, null, null, null, null, null, null, null, null, null, null, null, null, null, null, null, null, null, null, null, null, null, null, null, null, null, null, null, null, null, null, null, null, null, null, null, null, null, null, null, null, null, null, null, null, null, null, null, null, null, null, null, null, null, null, null, null, null, null, null, null, null, null, null, null, null, null, null, null, null, null, null, null, null, null, null, null, null, null, null, null, null, null, null, null, null, null, null, null, null, null, null, null, null, null, null, null, null, null, null, null, null, null, null, null, null, null, null, null, null, null, null, null, null, null, null, null, null, null, null, null, null, null, null, null, null, null, null, null, null, null], "gpr2b_Frankland": [null, null, null, null, null, null, null, null, null, null, null, null, null, null, null, null, null, 0.5, null, null, null, null, null, null, null, null, null, null, null, null, 0.5, null, null, null, null, null, null, null, null, null, null, null, null, null, null, null, null, null, null, null, null, 0.5, null, null, null, null, null, null, null, null, null, null, null, null, 0.625, null, null, null, null, null, null, null, null, null, null, null, null, null, 0.5, null, null, null, null, null, null, null, null, null, null, null, null, null, null, null, null, null, null, null, null, null, null, null, null, null, null, null, null, null, null, null, 0.5, null, null, null, null, null, null, null, null, null, null, null, null, null, null, null, null, null, null, null, null, null, null, null, null, null, null, null, null], "gpr3a_Frankland": [null, null, null, null, 0.5, null, null, 0.25, null, null, null, null, null, null, null, null, null, null, 0.8, null, null, null, 0.6666666666666667, null, null, null, null, 0.33333333333333337, null, null, null, null, null, null, 0.5, null, null, 0.25, null, null, null, null, null, null, null, null, null, null, null, null, null, null, null, null, 0.5, null, 0.7, null, 0.75, null, 0.75, null, 0.5, null, 0.9117647058823529, null, null, null, null, 0.4, null, null, null, 0.30000000000000004, null, null, 0.8571428571428572, null, null, null, null, null, null, null, null, 0.6666666666666667, null, null, null, null, null, null, null, 0.6, null, null, 1.0, null, 0.9666666666666667, null, null, 0.4, null, null, null, 0.30000000000000004, null, null, 0.8571428571428572, null, null, null, null, null, null, null, null, 0.5, null, null, null, 0.33333333333333337, null, null, 0.33333333333333337, null, null, 0.75, null, null, 0.65, null, 0.33333333333333337, null, null, null, 0.30000000000000004, null, null], "gpr3d_Frankland": [null, null, 0.0, 0.0, 0.0, 0.0, 0.0, 0.0, 0.0, 0.0, 0.0, 0.0, 0.0, 0.0, 0.0, null, null, null, null, 0.0, 0.0, 0.0, 0.0, 0.0, 0.0, 0.0, 0.0, 0.0, null, null, null, null, 0.0, 0.0, 0.0, 0.0, 0.0, 0.0, 0.0, 0.0, 0.0, 0.0, 0.0, 0.0, 0.0, 0.0, 0.0, 0.0, 0.0, null, null, null, null, 0.0, 0.0, null, 0.5, null, 0.5, null, 0.0, 0.0, null, null, null, null, 0.5, null, 0.0, 0.0, 0.0, 0.0, 0.0, 0.0, 0.0, 0.0, null, null, null, null, 0.0, 0.0, 0.0, 0.0, 0.0, 0.0, 0.0, 0.0, 0.0, null, 0.5, null, 0.5, null, 0.0, 0.0, 0.0, 0.0, 0.0, 0.0, 0.0, 0.0, 0.0, 0.0, 0.0, 0.0, 0.0, 0.0, null, null, null, null, 0.0, 0.0, 0.0, 0.0, 0.0, 0.0, 0.0, 0.0, 0.0, 0.0, 0.0, 0.0, 0.0, 0.0, 0.0, 0.0, 0.0, 0.0, 0.0, 0.0, 0.0, 0.0, 0.0, 0.0, null, null, null], "gpr_Frankland_sum": [0, 0, 0, 0, 0.5, 0, 0, 0.25, 0, 0, 0, 0, 0, 0, 0, 0, 0, 0.5, 0.8, 0, 0, 0, 0.6666666666666667, 0, 0, 0, 0, 0.33333333333333337, 0, 0, 0.5, 0, 0, 0, 0.5, 0, 0, 0.25, 0, 0, 0, 0, 0, 0, 0, 0, 0, 0, 0, 0, 0, 0.5, 0, 0, 0.5, 0, 1.2, 0, 1.25, 0, 0.75, 0, 0.5, 0, 1.5367647058823528, 0, 0.5, 0, 0, 0.4, 0, 0, 0, 0.30000000000000004, 0, 0, 0.8571428571428572, 0, 0.5, 0, 0, 0, 0, 0, 0, 0.6666666666666667, 0, 0, 0, 0, 0.5, 0, 0.5, 0.6, 0, 0, 1.0, 0, 0.9666666666666667, 0, 0, 0.4, 0, 0, 0, 0.30000000000000004, 0, 0, 0.8571428571428572, 0, 0.5, 0, 0, 0, 0, 0, 0, 0.5, 0, 0, 0, 0.33333333333333337, 0, 0, 0.33333333333333337, 0, 0, 0.75, 0, 0, 0.65, 0, 0.33333333333333337, 0, 0, 0, 0.30000000000000004, 0, 0], "lbdm_spitch": [null, 0.05239520958083833, 0.031437125748503, 0.031437125748503, 0.13972055888223553, 0.0499001996007984, 0.03992015968063872, 0.04657351962741184, 0.01746506986027944, 0.05239520958083833, 0.01746506986027944, 0.010479041916167666, 0.02095808383233533, 0.026197604790419163, 0.05239520958083833, 0.13972055888223553, 0.0, 0.16766467065868265, 0.6072470443727928, 0.04675264854905573, 0.02095808383233533, 0.014970059880239521, 0.11676646706586827, 0.0, 0.05239520958083833, 0.0, 0.014970059880239521, 0.04491017964071856, 0.014970059880239521, 0.03493013972055888, 0.0873253493013972, 0.05239520958083833, 0.031437125748503, 0.031437125748503, 0.13972055888223553, 0.0499001996007984, 0.03992015968063872, 0.04657351962741184, 0.01746506986027944, 0.05239520958083833, 0.01746506986027944, 0.010479041916167666, 0.02095808383233533, 0.026197604790419163, 0.05239520958083833, 0.01905280348394121, 0.023816004354926514, 0.05239520958083833, 0.031437125748503, 0.09431137724550898, 0.0, 0.05239520958083833, 0.02095808383233533, 0.027944111776447105, 0.0748502994011976, 0.0499001996007984, 0.21831337325349298, 0.036676646706586824, 0.07335329341317365, 0.0, 0.07335329341317365, 0.027944111776447105, 0.0748502994011976, 0.08046407185628741, 0.8540419161676647, 0.04890219560878244, 0.02095808383233533, 0.026197604790419163, 0.07144801306477953, 0.11114135365632372, 0.05588822355289421, 0.027944111776447105, 0.08383233532934133, 0.07621121393576484, 0.07144801306477953, 0.07382961350027219, 0.4519748382023831, 0.0, 0.2852628077178975, 0.0, 0.12225548902195607, 0.10479041916167665, 0.027944111776447105, 0.02095808383233533, 0.014970059880239521, 0.11676646706586827, 0.0, 0.06736526946107783, 0.02245508982035928, 0.02245508982035928, 0.014970059880239521, 0.02095808383233533, 0.036676646706586824, 0.18338323353293415, 0.125748502994012, 0.0, 0.10479041916167665, 0.0, 1.0, 0.060878243512974044, 0.10887316276537833, 0.11114135365632372, 0.05588822355289421, 0.027944111776447105, 0.08383233532934133, 0.07621121393576484, 0.07144801306477953, 0.07382961350027219, 0.4519748382023831, 0.0, 0.2852628077178975, 0.0, 0.16671203048448557, 0.06859009254218836, 0.010479041916167666, 0.010479041916167666, 0.03592814371257485, 0.0748502994011976, 0.027944111776447105, 0.02095808383233533, 0.014970059880239521, 0.04491017964071856, 0.014970059880239521, 0.014970059880239521, 0.04491017964071856, 0.014970059880239521, 0.026197604790419163, 0.19211576846307385, 0.0, 0.2641775272983445, 0.45350475519549144, 0.0748502994011976, 0.04491017964071856, 0.014970059880239521, 0.026197604790419163, 0.07144801306477953, 0.07621121393576484, null, null], "lbdm_sioi": [null, 0.17857142857142855, 0.0, 0.0, 0.0, 0.0, 0.0, 0.0, 0.0, 0.0, 0.0, 0.0, 0.0, 0.0, 0.0, 0.0, 0.17857142857142855, 0.7142857142857142, 0.17857142857142855, 0.0, 0.0, 0.0, 0.0, 0.0, 0.0, 0.0, 0.0, 0.0, 0.0, 0.17857142857142855, 0.7142857142857142, 0.17857142857142855, 0.0, 0.0, 0.0, 0.0, 0.0, 0.0, 0.0, 0.0, 0.0, 0.0, 0.0, 0.0, 0.0, 0.0, 0.0, 0.0, 0.0, 0.0, 0.17857142857142855, 0.7142857142857142, 0.17857142857142855, 0.0, 0.0, 0.0, 0.17857142857142855, 0.08928571428571427, 0.08928571428571427, 0.17857142857142855, 0.0, 0.0, 0.0, 0.17857142857142855, 1.0, 0.1607142857142857, 0.08928571428571427, 0.17857142857142855, 0.0, 0.0, 0.0, 0.0, 0.0, 0.0, 0.0, 0.0, 0.0, 0.17857142857142855, 0.7142857142857142, 0.17857142857142855, 0.0, 0.0, 0.0, 0.0, 0.0, 0.0, 0.0, 0.0, 0.0, 0.0, 0.17857142857142855, 0.08928571428571427, 0.08928571428571427, 0.17857142857142855, 0.0, 0.0, 0.0, 0.0, 0.0, 0.0, 0.0, 0.0, 0.0, 0.0, 0.0, 0.0, 0.0, 0.0, 0.0, 0.17857142857142855, 0.7142857142857142, 0.17857142857142855, 0.0, 0.0, 0.0, 0.0, 0.0, 0.0, 0.0, 0.0, 0.0, 0.0, 0.0, 0.0, 0.0, 0.0, 0.0, 0.0, 0.0, 0.0, 0.0, 0.0, 0.0, 0.0, 0.0, 0.0, 0.0, null, null], "lbdm_srest": [null, 0.0, 0.0, 0.0, 0.0, 0.0, 0.0, 0.0, 0.0, 0.0, 0.0, 0.0, 0.0, 0.0, 0.0, 0.0, 0.0, 0.0, 0.0, 0.0, 0.0, 0.0, 0.0, 0.0, 0.0, 0.0, 0.0, 0.0, 0.0, 0.0, 0.0, 0.0, 0.0, 0.0, 0.0, 0.0, 0.0, 0.0, 0.0, 0.0, 0.0, 0.0, 0.0, 0.0, 0.0, 0.0, 0.0, 0.0, 0.0, 0.0, 0.0, 0.0, 0.0, 0.0, 0.0, 0.0, 0.0, 0.0, 0.0, 0.0, 0.0, 0.0, 0.0, 0.0, 0.0, 0.0, 0.0, 0.0, 0.0, 0.0, 0.0, 0.0, 0.0, 0.0, 0.0, 0.0, 0.0, 0.0, 0.0, 0.0, 0.0, 0.0, 0.0, 0.0, 0.0, 0.0, 0.0, 0.0, 0.0, 0.0, 0.0, 0.0, 0.0, 0.0, 0.0, 0.0, 0.0, 0.0, 0.0, 0.0, 0.0, 0.0, 0.0, 0.0, 0.0, 0.0, 0.0, 0.0, 0.0, 0.0, 0.0, 0.0, 0.0, 0.0, 0.0, 0.0, 0.0, 0.0, 0.0, 0.0, 0.0, 0.0, 0.0, 0.0, 0.0, 0.0, 0.0, 0.0, 0.0, 0.0, 0.0, 0.0, 0.0, 0.0, 0.0, 0.0, 0.0, null, null], "lbdm_rpitch": [null, 0.0, 0.2, 0.0, 0.2, 0.3333333333333333, 0.14285714285714285, 0.1111111111111111, 0.1111111111111111, 0.0, 0.3333333333333333, 0.0, 0.2, 0.0, 0.25, 0.0, 0.6666666666666666, 0.6, 0.4666666666666667, 0.6923076923076923, 0.2, 0.0, 0.14285714285714285, 0.6, 0.5, 0.0, 0.0, 0.14285714285714285, 0.14285714285714285, 0.0, 0.3333333333333333, 0.0, 0.2, 0.0, 0.2, 0.3333333333333333, 0.14285714285714285, 0.1111111111111111, 0.1111111111111111, 0.0, 0.3333333333333333, 0.0, 0.2, 0.0, 0.25, 0.0, 0.09090909090909091, 0.0, 0.2, 0.0, 0.6, 0.5, 0.0, 0.2, 0.3333333333333333, 0.14285714285714285, 0.3333333333333333, 0.5, 0.2, 0.5, 0.5, 0.2, 0.3333333333333333, 0.14285714285714285, 0.625, 0.7333333333333333, 0.2, 0.0, 0.25, 0.09090909090909091, 0.3333333333333333, 0.2, 0.3333333333333333, 0.2, 0.09090909090909091, 0.25, 0.45454545454545453, 0.7777777777777778, 0.7777777777777778, 0.0, 0.0, 0.3333333333333333, 0.3333333333333333, 0.2, 0.0, 0.14285714285714285, 0.6, 0.5, 0.14285714285714285, 0.0, 0.14285714285714285, 0.0, 0.2, 0.5, 0.2, 0.6, 0.5, 0.5, 0.8571428571428571, 0.7333333333333333, 0.42857142857142855, 0.09090909090909091, 0.3333333333333333, 0.2, 0.3333333333333333, 0.2, 0.09090909090909091, 0.25, 0.45454545454545453, 0.7777777777777778, 0.7777777777777778, 0.0, 0.0, 0.45454545454545453, 0.2, 0.0, 0.2, 0.14285714285714285, 0.3333333333333333, 0.2, 0.0, 0.14285714285714285, 0.14285714285714285, 0.0, 0.14285714285714285, 0.14285714285714285, 0.0, 0.25, 0.6666666666666666, 0.7142857142857143, 0.29411764705882354, 0.5714285714285714, 0.14285714285714285, 0.14285714285714285, 0.0, 0.25, 0.09090909090909091, 0.2, null], "lbdm_rioi": [null, 0.3333333333333333, 0.0, 0.0, 0.0, 0.0, 0.0, 0.0, 0.0, 0.0, 0.0, 0.0, 0.0, 0.0, 0.0, 0.0, 0.0, 0.3333333333333333, 0.3333333333333333, 0.0, 0.0, 0.0, 0.0, 0.0, 0.0, 0.0, 0.0, 0.0, 0.0, 0.0, 0.3333333333333333, 0.3333333333333333, 0.0, 0.0, 0.0, 0.0, 0.0, 0.0, 0.0, 0.0, 0.0, 0.0, 0.0, 0.0, 0.0, 0.0, 0.0, 0.0, 0.0, 0.0, 0.0, 0.3333333333333333, 0.3333333333333333, 0.0, 0.0, 0.0, 0.0, 0.3333333333333333, 0.0, 0.3333333333333333, 0.0, 0.0, 0.0, 0.0, 0.3333333333333333, 0.6, 0.0, 0.3333333333333333, 0.0, 0.0, 0.0, 0.0, 0.0, 0.0, 0.0, 0.0, 0.0, 0.0, 0.3333333333333333, 0.3333333333333333, 0.0, 0.0, 0.0, 0.0, 0.0, 0.0, 0.0, 0.0, 0.0, 0.0, 0.0, 0.3333333333333333, 0.0, 0.3333333333333333, 0.0, 0.0, 0.0, 0.0, 0.0, 0.0, 0.0, 0.0, 0.0, 0.0, 0.0, 0.0, 0.0, 0.0, 0.0, 0.0, 0.3333333333333333, 0.3333333333333333, 0.0, 0.0, 0.0, 0.0, 0.0, 0.0, 0.0, 0.0, 0.0, 0.0, 0.0, 0.0, 0.0, 0.0, 0.0, 0.0, 0.0, 0.0, 0.0, 0.0, 0.0, 0.0, 0.0, 0.0, 0.0, 0.0, null], "lbdm_rrest": [null, 0.0, 0.0, 0.0, 0.0, 0.0, 0.0, 0.0, 0.0, 0.0, 0.0, 0.0, 0.0, 0.0, 0.0, 0.0, 0.0, 0.0, 0.0, 0.0, 0.0, 0.0, 0.0, 0.0, 0.0, 0.0, 0.0, 0.0, 0.0, 0.0, 0.0, 0.0, 0.0, 0.0, 0.0, 0.0, 0.0, 0.0, 0.0, 0.0, 0.0, 0.0, 0.0, 0.0, 0.0, 0.0, 0.0, 0.0, 0.0, 0.0, 0.0, 0.0, 0.0, 0.0, 0.0, 0.0, 0.0, 0.0, 0.0, 0.0, 0.0, 0.0, 0.0, 0.0, 0.0, 0.0, 0.0, 0.0, 0.0, 0.0, 0.0, 0.0, 0.0, 0.0, 0.0, 0.0, 0.0, 0.0, 0.0, 0.0, 0.0, 0.0, 0.0, 0.0, 0.0, 0.0, 0.0, 0.0, 0.0, 0.0, 0.0, 0.0, 0.0, 0.0, 0.0, 0.0, 0.0, 0.0, 0.0, 0.0, 0.0, 0.0, 0.0, 0.0, 0.0, 0.0, 0.0, 0.0, 0.0, 0.0, 0.0, 0.0, 0.0, 0.0, 0.0, 0.0, 0.0, 0.0, 0.0, 0.0, 0.0, 0.0, 0.0, 0.0, 0.0, 0.0, 0.0, 0.0, 0.0, 0.0, 0.0, 0.0, 0.0, 0.0, 0.0, 0.0, 0.0, 0.0, null], "lbdm_boundarystrength": [null, 0.10238451668092385, 0.00785928143712575, 0.00785928143712575, 0.03493013972055888, 0.0124750499001996, 0.00998003992015968, 0.01164337990685296, 0.00436626746506986, 0.013098802395209582, 0.00436626746506986, 0.0026197604790419164, 0.005239520958083833, 0.006549401197604791, 0.013098802395209582, 0.03493013972055888, 0.08928571428571427, 0.39905902480752775, 0.24109747537891246, 0.011688162137263933, 0.005239520958083833, 0.0037425149700598802, 0.029191616766467067, 0.0, 0.013098802395209582, 0.0, 0.0037425149700598802, 0.01122754491017964, 0.0037425149700598802, 0.09801824921585399, 0.3789741944682064, 0.10238451668092385, 0.00785928143712575, 0.00785928143712575, 0.03493013972055888, 0.0124750499001996, 0.00998003992015968, 0.01164337990685296, 0.00436626746506986, 0.013098802395209582, 0.00436626746506986, 0.0026197604790419164, 0.005239520958083833, 0.006549401197604791, 0.013098802395209582, 0.0047632008709853025, 0.005954001088731628, 0.013098802395209582, 0.00785928143712575, 0.023577844311377244, 0.08928571428571427, 0.3702416595380667, 0.0945252352437981, 0.006986027944111776, 0.0187125748502994, 0.0124750499001996, 0.14386405759908752, 0.05381201881950384, 0.06298118049615055, 0.08928571428571427, 0.018338323353293412, 0.006986027944111776, 0.0187125748502994, 0.10940173224978612, 0.7135104790419162, 0.09258269175933846, 0.04988237810094097, 0.09583511548331906, 0.017862003266194883, 0.02778533841408093, 0.013972055888223553, 0.006986027944111776, 0.02095808383233533, 0.01905280348394121, 0.017862003266194883, 0.018457403375068047, 0.11299370955059578, 0.08928571428571427, 0.4284585590723315, 0.08928571428571427, 0.030563872255489018, 0.026197604790419163, 0.006986027944111776, 0.005239520958083833, 0.0037425149700598802, 0.029191616766467067, 0.0, 0.01684131736526946, 0.00561377245508982, 0.00561377245508982, 0.09302822925577416, 0.04988237810094097, 0.05381201881950384, 0.13513152266894782, 0.031437125748503, 0.0, 0.026197604790419163, 0.0, 0.25, 0.015219560878243511, 0.02721829069134458, 0.02778533841408093, 0.013972055888223553, 0.006986027944111776, 0.02095808383233533, 0.01905280348394121, 0.017862003266194883, 0.018457403375068047, 0.11299370955059578, 0.08928571428571427, 0.4284585590723315, 0.08928571428571427, 0.04167800762112139, 0.01714752313554709, 0.0026197604790419164, 0.0026197604790419164, 0.008982035928143712, 0.0187125748502994, 0.006986027944111776, 0.005239520958083833, 0.0037425149700598802, 0.01122754491017964, 0.0037425149700598802, 0.0037425149700598802, 0.01122754491017964, 0.0037425149700598802, 0.006549401197604791, 0.04802894211576846, 0.0, 0.06604438182458612, 0.11337618879887286, 0.0187125748502994, 0.01122754491017964, 0.0037425149700598802, 0.006549401197604791, 0.017862003266194883, 0.01905280348394121, null, null]}}
