{"id": "SES018312", "tunefamily": "", "year": -1, "tunefamily_full": "", "type": "", "freemeter": false, "origin": "", "features": {"scaledegree": [5, 1, 2, 3, 2, 3, 4, 3, 7, 5, 4, 3, 2, 1, 2, 3, 4, 3, 4, 5, 5, 3, 1, 3, 2, 7, 2, 1, 2, 3, 2, 1, 7, 1, 5, 6, 7, 4, 7, 1, 2, 3, 2, 3, 4, 3, 2, 1, 2, 1, 7, 1, 1, 1], "scaledegreespecifier": ["P", "P", "M", "m", "M", "m", "P", "m", "m", "P", "P", "m", "M", "P", "M", "m", "P", "m", "P", "P", "P", "m", "P", "m", "M", "m", "M", "P", "M", "m", "M", "P", "m", "P", "P", "M", "m", "P", "m", "P", "M", "m", "M", "m", "P", "m", "M", "P", "M", "P", "m", "P", "P", "P"], "tonic": ["E", "E", "E", "E", "E", "E", "E", "E", "E", "E", "E", "E", "E", "E", "E", "E", "E", "E", "E", "E", "E", "E", "E", "E", "E", "E", "E", "E", "E", "E", "E", "E", "E", "E", "E", "E", "E", "E", "E", "E", "E", "E", "E", "E", "E", "E", "E", "E", "E", "E", "E", "E", "E", "E"], "mode": ["minor", "minor", "minor", "minor", "minor", "minor", "minor", "minor", "minor", "minor", "minor", "minor", "minor", "minor", "minor", "minor", "minor", "minor", "minor", "minor", "minor", "minor", "minor", "minor", "minor", "minor", "minor", "minor", "minor", "minor", "minor", "minor", "minor", "minor", "minor", "minor", "minor", "minor", "minor", "minor", "minor", "minor", "minor", "minor", "minor", "minor", "minor", "minor", "minor", "minor", "minor", "minor", "minor", "minor"], "metriccontour": [null, "+", "-", "+", "+", "-", "+", "+", "-", "+", "-", "+", "-", "+", "-", "+", "+", "-", "+", "+", "=", "=", "=", "-", "+", "=", "-", "+", "-", "+", "+", "-", "=", "+", "=", "-", "+", "=", "-", "+", "-", "+", "+", "-", "+", "+", "-", "+", "+", "-", "+", "+", "-", "+"], "imaweight": [0.514, 0.224, 0.114, 0.226, 0.234, 0.112, 0.474, 0.218, 0.132, 0.244, 0.086, 0.274, 0.392, 0.204, 0.106, 0.316, 0.226, 0.082, 0.484, 0.228, 0.888, 0.852, 0.884, 0.264, 0.808, 0.872, 0.23, 0.814, 0.14, 0.162, 0.888, 0.188, 0.186, 0.828, 0.852, 0.172, 0.798, 0.918, 0.18, 0.85, 0.194, 0.13, 1.0, 0.178, 0.17, 0.958, 0.144, 0.098, 0.936, 0.188, 0.202, 0.928, 0.162, 0.408], "imaweight_spectral": [1.0, 0.282645, 0.135537, 0.909091, 0.276033, 0.140496, 0.930579, 0.26281, 0.135537, 0.882645, 0.0710744, 0.294215, 0.904132, 0.305785, 0.161983, 0.928926, 0.287603, 0.142149, 0.975207, 0.310744, 0.953719, 0.996694, 0.950413, 0.307438, 0.909091, 0.955372, 0.271074, 0.88595, 0.25124, 0.190083, 0.935537, 0.315702, 0.195041, 0.892562, 0.952066, 0.216529, 0.887603, 0.978512, 0.203306, 0.846281, 0.203306, 0.17686, 0.947107, 0.175207, 0.218182, 0.955372, 0.161983, 0.143802, 0.887603, 0.183471, 0.242975, 0.917355, 0.221488, 0.950413], "pitch40_hewlett": [158, 175, 181, 186, 181, 186, 192, 186, 169, 158, 152, 146, 141, 135, 141, 146, 152, 146, 152, 158, 158, 186, 175, 186, 181, 169, 181, 175, 181, 186, 181, 175, 169, 175, 158, 164, 169, 152, 169, 175, 181, 186, 181, 186, 192, 186, 181, 175, 181, 175, 169, 175, 175, 175], "pitch40_sapp": [197, 214, 220, 225, 220, 225, 231, 225, 208, 197, 191, 185, 180, 174, 180, 185, 191, 185, 191, 197, 197, 225, 214, 225, 220, 208, 220, 214, 220, 225, 220, 214, 208, 214, 197, 203, 208, 191, 208, 214, 220, 225, 220, 225, 231, 225, 220, 214, 220, 214, 208, 214, 214, 214], "octave": [4, 5, 5, 5, 5, 5, 5, 5, 5, 4, 4, 4, 4, 4, 4, 4, 4, 4, 4, 4, 4, 5, 5, 5, 5, 5, 5, 5, 5, 5, 5, 5, 5, 5, 4, 5, 5, 4, 5, 5, 5, 5, 5, 5, 5, 5, 5, 5, 5, 5, 5, 5, 5, 5], "midipitch": [71, 76, 78, 79, 78, 79, 81, 79, 74, 71, 69, 67, 66, 64, 66, 67, 69, 67, 69, 71, 71, 79, 76, 79, 78, 74, 78, 76, 78, 79, 78, 76, 74, 76, 71, 73, 74, 69, 74, 76, 78, 79, 78, 79, 81, 79, 78, 76, 78, 76, 74, 76, 76, 76], "diatonicpitch": [32, 35, 36, 37, 36, 37, 38, 37, 34, 32, 31, 30, 29, 28, 29, 30, 31, 30, 31, 32, 32, 37, 35, 37, 36, 34, 36, 35, 36, 37, 36, 35, 34, 35, 32, 33, 34, 31, 34, 35, 36, 37, 36, 37, 38, 37, 36, 35, 36, 35, 34, 35, 35, 35], "diatonicinterval": [null, 3, 1, 1, -1, 1, 1, -1, -3, -2, -1, -1, -1, -1, 1, 1, 1, -1, 1, 1, 0, 5, -2, 2, -1, -2, 2, -1, 1, 1, -1, -1, -1, 1, -3, 1, 1, -3, 3, 1, 1, 1, -1, 1, 1, -1, -1, -1, 1, -1, -1, 1, 0, 0], "chromaticinterval": [null, 5, 2, 1, -1, 1, 2, -2, -5, -3, -2, -2, -1, -2, 2, 1, 2, -2, 2, 2, 0, 8, -3, 3, -1, -4, 4, -2, 2, 1, -1, -2, -2, 2, -5, 2, 1, -5, 5, 2, 2, 1, -1, 1, 2, -2, -1, -2, 2, -2, -2, 2, 0, 0], "pitchproximity": [null, null, 2, 1, 1, 1, 2, 2, 5, 3, 2, 2, 1, 2, 2, 1, 2, 2, 2, 2, 0, 8, 3, 3, 1, 4, 4, 2, 2, 1, 1, 2, 2, 2, 5, 2, 1, 5, 5, 2, 2, 1, 1, 1, 2, 2, 1, 2, 2, 2, 2, 2, 0, 0], "pitchreversal": [null, null, 0, 0, 1.5, 1.5, 0, 1.5, 0, 0, 0, 0, 0, 0, 1.5, 0, 0, 1.5, 1.5, 0, 0, 0, 1, 1.5, 1.5, 0, 1.5, 1.5, 1.5, 0, 1.5, 0, 0, 1.5, 0, 0, 0, 0, 1.5, 0, 0, 0, 1.5, 1.5, 0, 1.5, 0, 0, 1.5, 1.5, 0, 1.5, 0, 0], "nextisrest": [false, false, false, false, false, false, false, false, false, false, false, false, false, false, false, false, false, false, false, false, false, false, false, false, false, false, false, false, false, false, false, false, false, false, false, false, false, false, false, false, false, false, false, false, false, false, false, false, false, false, false, false, false, null], "restduration_frac": [null, null, null, null, null, null, null, null, null, null, null, null, null, null, null, null, null, null, null, null, null, null, null, null, null, null, null, null, null, null, null, null, null, null, null, null, null, null, null, null, null, null, null, null, null, null, null, null, null, null, null, null, null, null], "duration": [1.0, 1.5, 0.5, 1.0, 1.5, 0.5, 1.0, 1.5, 0.5, 0.5, 0.5, 2.0, 1.0, 1.5, 0.5, 1.0, 1.5, 0.5, 1.0, 5.0, 3.0, 3.0, 2.0, 1.0, 3.0, 2.0, 1.0, 1.5, 0.5, 1.0, 1.0, 1.0, 1.0, 3.0, 2.0, 1.0, 3.0, 2.0, 1.0, 1.5, 0.5, 1.0, 1.5, 0.5, 1.0, 1.5, 0.5, 1.0, 1.5, 0.5, 1.0, 5.0, 1.0, 2.0], "duration_frac": ["1", "3/2", "1/2", "1", "3/2", "1/2", "1", "3/2", "1/2", "1/2", "1/2", "2", "1", "3/2", "1/2", "1", "3/2", "1/2", "1", "5", "3", "3", "2", "1", "3", "2", "1", "3/2", "1/2", "1", "1", "1", "1", "3", "2", "1", "3", "2", "1", "3/2", "1/2", "1", "3/2", "1/2", "1", "3/2", "1/2", "1", "3/2", "1/2", "1", "5", "1", "2"], "duration_fullname": ["Quarter", "Dotted Quarter", "Eighth", "Quarter", "Dotted Quarter", "Eighth", "Quarter", "Dotted Quarter", "Eighth", "Eighth", "Eighth", "Half", "Quarter", "Dotted Quarter", "Eighth", "Quarter", "Dotted Quarter", "Eighth", "Quarter", "Whole tied to Quarter (5 total QL)", "Dotted Half", "Dotted Half", "Half", "Quarter", "Dotted Half", "Half", "Quarter", "Dotted Quarter", "Eighth", "Quarter", "Quarter", "Quarter", "Quarter", "Dotted Half", "Half", "Quarter", "Dotted Half", "Half", "Quarter", "Dotted Quarter", "Eighth", "Quarter", "Dotted Quarter", "Eighth", "Quarter", "Dotted Quarter", "Eighth", "Quarter", "Dotted Quarter", "Eighth", "Quarter", "Whole tied to Quarter (5 total QL)", "Quarter", "Half"], "durationcontour": [null, "+", "-", "+", "+", "-", "+", "+", "-", "=", "=", "+", "-", "+", "-", "+", "+", "-", "+", "+", "-", "=", "-", "-", "+", "-", "-", "+", "-", "+", "=", "=", "=", "+", "-", "-", "+", "-", "-", "+", "-", "+", "+", "-", "+", "+", "-", "+", "+", "-", "+", "+", "-", "+"], "onsettick": [0, 2, 5, 6, 8, 11, 12, 14, 17, 18, 19, 20, 24, 26, 29, 30, 32, 35, 36, 38, 48, 54, 60, 64, 66, 72, 76, 78, 81, 82, 84, 86, 88, 90, 96, 100, 102, 108, 112, 114, 117, 118, 120, 123, 124, 126, 129, 130, 132, 135, 136, 138, 148, 150], "beatfraction": ["1", "3/2", "1/2", "1", "3/2", "1/2", "1", "3/2", "1/2", "1/2", "1/2", "2", "1", "3/2", "1/2", "1", "3/2", "1/2", "1", "5", "3", "3", "2", "1", "3", "2", "1", "3/2", "1/2", "1", "1", "1", "1", "3", "2", "1", "3", "2", "1", "3/2", "1/2", "1", "3/2", "1/2", "1", "3/2", "1/2", "1", "3/2", "1/2", "1", "5", "1", "2"], "phrasepos": [0.0, 0.041666666666666664, 0.10416666666666667, 0.125, 0.16666666666666666, 0.22916666666666666, 0.25, 0.2916666666666667, 0.3541666666666667, 0.375, 0.3958333333333333, 0.4166666666666667, 0.5, 0.5416666666666666, 0.6041666666666666, 0.625, 0.6666666666666666, 0.7291666666666666, 0.75, 0.7916666666666666, 1.0, 0.0, 0.13043478260869565, 0.21739130434782608, 0.2608695652173913, 0.391304347826087, 0.4782608695652174, 0.5217391304347826, 0.5869565217391305, 0.6086956521739131, 0.6521739130434783, 0.6956521739130435, 0.7391304347826086, 0.782608695652174, 0.9130434782608695, 1.0, 0.0, 0.125, 0.20833333333333334, 0.25, 0.3125, 0.3333333333333333, 0.375, 0.4375, 0.4583333333333333, 0.5, 0.5625, 0.5833333333333334, 0.625, 0.6875, 0.7083333333333334, 0.75, 0.9583333333333334, 1.0], "phrase_ix": [0, 0, 0, 0, 0, 0, 0, 0, 0, 0, 0, 0, 0, 0, 0, 0, 0, 0, 0, 0, 0, 1, 1, 1, 1, 1, 1, 1, 1, 1, 1, 1, 1, 1, 1, 1, 2, 2, 2, 2, 2, 2, 2, 2, 2, 2, 2, 2, 2, 2, 2, 2, 2, 2], "phrase_end": [false, false, false, false, false, false, false, false, false, false, false, false, false, false, false, false, false, false, false, false, true, false, false, false, false, false, false, false, false, false, false, false, false, false, false, true, false, false, false, false, false, false, false, false, false, false, false, false, false, false, false, false, false, true], "songpos": [0.0, 0.013333333333333334, 0.03333333333333333, 0.04, 0.05333333333333334, 0.07333333333333333, 0.08, 0.09333333333333334, 0.11333333333333333, 0.12, 0.12666666666666668, 0.13333333333333333, 0.16, 0.17333333333333334, 0.19333333333333333, 0.2, 0.21333333333333335, 0.23333333333333334, 0.24, 0.25333333333333335, 0.32, 0.36, 0.4, 0.4266666666666667, 0.44, 0.48, 0.5066666666666667, 0.52, 0.54, 0.5466666666666666, 0.56, 0.5733333333333334, 0.5866666666666667, 0.6, 0.64, 0.6666666666666666, 0.68, 0.72, 0.7466666666666667, 0.76, 0.78, 0.7866666666666666, 0.8, 0.82, 0.8266666666666667, 0.84, 0.86, 0.8666666666666667, 0.88, 0.9, 0.9066666666666666, 0.92, 0.9866666666666667, 1.0], "beatinsong": ["-1", "0", "3/2", "2", "3", "9/2", "5", "6", "15/2", "8", "17/2", "9", "11", "12", "27/2", "14", "15", "33/2", "17", "18", "23", "26", "29", "31", "32", "35", "37", "38", "79/2", "40", "41", "42", "43", "44", "47", "49", "50", "53", "55", "56", "115/2", "58", "59", "121/2", "61", "62", "127/2", "64", "65", "133/2", "67", "68", "73", "74"], "beatinphrase": ["-1", "0", "3/2", "2", "3", "9/2", "5", "6", "15/2", "8", "17/2", "9", "11", "12", "27/2", "14", "15", "33/2", "17", "18", "23", "0", "3", "5", "6", "9", "11", "12", "27/2", "14", "15", "16", "17", "18", "21", "23", "0", "3", "5", "6", "15/2", "8", "9", "21/2", "11", "12", "27/2", "14", "15", "33/2", "17", "18", "23", "24"], "beatinphrase_end": ["-24", "-23", "-43/2", "-21", "-20", "-37/2", "-18", "-17", "-31/2", "-15", "-29/2", "-14", "-12", "-11", "-19/2", "-9", "-8", "-13/2", "-6", "-5", "0", "-21", "-18", "-16", "-15", "-12", "-10", "-9", "-15/2", "-7", "-6", "-5", "-4", "-3", "0", "2", "-24", "-21", "-19", "-18", "-33/2", "-16", "-15", "-27/2", "-13", "-12", "-21/2", "-10", "-9", "-15/2", "-7", "-6", "-1", "0"], "IOI_frac": ["1", "3/2", "1/2", "1", "3/2", "1/2", "1", "3/2", "1/2", "1/2", "1/2", "2", "1", "3/2", "1/2", "1", "3/2", "1/2", "1", "5", "3", "3", "2", "1", "3", "2", "1", "3/2", "1/2", "1", "1", "1", "1", "3", "2", "1", "3", "2", "1", "3/2", "1/2", "1", "3/2", "1/2", "1", "3/2", "1/2", "1", "3/2", "1/2", "1", "5", "1", null], "IOI": [1.0, 1.5, 0.5, 1.0, 1.5, 0.5, 1.0, 1.5, 0.5, 0.5, 0.5, 2.0, 1.0, 1.5, 0.5, 1.0, 1.5, 0.5, 1.0, 5.0, 3.0, 3.0, 2.0, 1.0, 3.0, 2.0, 1.0, 1.5, 0.5, 1.0, 1.0, 1.0, 1.0, 3.0, 2.0, 1.0, 3.0, 2.0, 1.0, 1.5, 0.5, 1.0, 1.5, 0.5, 1.0, 1.5, 0.5, 1.0, 1.5, 0.5, 1.0, 5.0, 1.0, null], "IOR_frac": [null, "3/2", "1/3", "2", "3/2", "1/3", "2", "3/2", "1/3", "1", "1", "4", "1/2", "3/2", "1/3", "2", "3/2", "1/3", "2", "5", "3/5", "1", "2/3", "1/2", "3", "2/3", "1/2", "3/2", "1/3", "2", "1", "1", "1", "3", "2/3", "1/2", "3", "2/3", "1/2", "3/2", "1/3", "2", "3/2", "1/3", "2", "3/2", "1/3", "2", "3/2", "1/3", "2", "5", "1/5", null], "IOR": [null, 1.5, 0.3333333333333333, 2.0, 1.5, 0.3333333333333333, 2.0, 1.5, 0.3333333333333333, 1.0, 1.0, 4.0, 0.5, 1.5, 0.3333333333333333, 2.0, 1.5, 0.3333333333333333, 2.0, 5.0, 0.6, 1.0, 0.6666666666666666, 0.5, 3.0, 0.6666666666666666, 0.5, 1.5, 0.3333333333333333, 2.0, 1.0, 1.0, 1.0, 3.0, 0.6666666666666666, 0.5, 3.0, 0.6666666666666666, 0.5, 1.5, 0.3333333333333333, 2.0, 1.5, 0.3333333333333333, 2.0, 1.5, 0.3333333333333333, 2.0, 1.5, 0.3333333333333333, 2.0, 5.0, 0.2, null], "imacontour": [null, "-", "-", "+", "+", "-", "+", "-", "-", "+", "-", "+", "+", "-", "-", "+", "-", "-", "+", "-", "+", "-", "+", "-", "+", "+", "-", "+", "-", "+", "+", "-", "-", "+", "+", "-", "+", "+", "-", "+", "-", "-", "+", "-", "-", "+", "-", "-", "+", "-", "+", "+", "-", "+"], "pitch": ["B4", "E5", "F#5", "G5", "F#5", "G5", "A5", "G5", "D5", "B4", "A4", "G4", "F#4", "E4", "F#4", "G4", "A4", "G4", "A4", "B4", "B4", "G5", "E5", "G5", "F#5", "D5", "F#5", "E5", "F#5", "G5", "F#5", "E5", "D5", "E5", "B4", "C#5", "D5", "A4", "D5", "E5", "F#5", "G5", "F#5", "G5", "A5", "G5", "F#5", "E5", "F#5", "E5", "D5", "E5", "E5", "E5"], "contour3": [null, "+", "+", "+", "-", "+", "+", "-", "-", "-", "-", "-", "-", "-", "+", "+", "+", "-", "+", "+", "=", "+", "-", "+", "-", "-", "+", "-", "+", "+", "-", "-", "-", "+", "-", "+", "+", "-", "+", "+", "+", "+", "-", "+", "+", "-", "-", "-", "+", "-", "-", "+", "=", "="], "contour5": [null, "++", "+", "+", "-", "+", "+", "-", "--", "--", "-", "-", "-", "-", "+", "+", "+", "-", "+", "+", "=", "++", "--", "++", "-", "--", "++", "-", "+", "+", "-", "-", "-", "+", "--", "+", "+", "--", "++", "+", "+", "+", "-", "+", "+", "-", "-", "-", "+", "-", "-", "+", "=", "="], "beatstrength": [0.5, 1.0, 0.25, 0.5, 1.0, 0.25, 0.5, 1.0, 0.25, 0.5, 0.25, 1.0, 0.5, 1.0, 0.25, 0.5, 1.0, 0.25, 0.5, 1.0, 1.0, 1.0, 1.0, 0.5, 1.0, 1.0, 0.5, 1.0, 0.25, 0.5, 1.0, 0.5, 0.5, 1.0, 1.0, 0.5, 1.0, 1.0, 0.5, 1.0, 0.25, 0.5, 1.0, 0.25, 0.5, 1.0, 0.25, 0.5, 1.0, 0.25, 0.5, 1.0, 0.5, 1.0], "beat_str": ["3", "1", "2", "3", "1", "2", "3", "1", "2", "3", "3", "1", "3", "1", "2", "3", "1", "2", "3", "1", "1", "1", "1", "3", "1", "1", "3", "1", "2", "3", "1", "2", "3", "1", "1", "3", "1", "1", "3", "1", "2", "3", "1", "2", "3", "1", "2", "3", "1", "2", "3", "1", "3", "1"], "beat_fraction_str": ["0", "0", "1/2", "0", "0", "1/2", "0", "0", "1/2", "0", "1/2", "0", "0", "0", "1/2", "0", "0", "1/2", "0", "0", "0", "0", "0", "0", "0", "0", "0", "0", "1/2", "0", "0", "0", "0", "0", "0", "0", "0", "0", "0", "0", "1/2", "0", "0", "1/2", "0", "0", "1/2", "0", "0", "1/2", "0", "0", "0", "0"], "beat": [3.0, 1.0, 2.5, 3.0, 1.0, 2.5, 3.0, 1.0, 2.5, 3.0, 3.5, 1.0, 3.0, 1.0, 2.5, 3.0, 1.0, 2.5, 3.0, 1.0, 1.0, 1.0, 1.0, 3.0, 1.0, 1.0, 3.0, 1.0, 2.5, 3.0, 1.0, 2.0, 3.0, 1.0, 1.0, 3.0, 1.0, 1.0, 3.0, 1.0, 2.5, 3.0, 1.0, 2.5, 3.0, 1.0, 2.5, 3.0, 1.0, 2.5, 3.0, 1.0, 3.0, 1.0], "timesignature": ["3/4", "3/4", "3/4", "3/4", "3/4", "3/4", "3/4", "3/4", "3/4", "3/4", "3/4", "3/4", "3/4", "3/4", "3/4", "3/4", "3/4", "3/4", "3/4", "3/4", "3/4", "3/4", "3/4", "3/4", "3/4", "3/4", "3/4", "3/4", "3/4", "3/4", "3/4", "3/4", "3/4", "3/4", "3/4", "3/4", "3/4", "3/4", "3/4", "3/4", "3/4", "3/4", "3/4", "3/4", "3/4", "3/4", "3/4", "3/4", "3/4", "3/4", "3/4", "3/4", "3/4", "3/4"], "gpr2a_Frankland": [null, null, null, null, null, null, null, null, null, null, null, null, null, null, null, null, null, null, null, null, null, null, null, null, null, null, null, null, null, null, null, null, null, null, null, null, null, null, null, null, null, null, null, null, null, null, null, null, null, null, null, null, null, null], "gpr2b_Frankland": [null, 0.5, null, null, 0.5, null, null, 0.5, null, null, null, 0.625, null, 0.5, null, null, 0.5, null, null, 0.6, null, null, null, null, 0.5, null, null, 0.5, null, null, null, null, null, 0.5, null, null, 0.5, null, null, 0.5, null, null, 0.5, null, null, 0.5, null, null, 0.5, null, null, 0.8, null, null], "gpr3a_Frankland": [null, null, null, null, null, null, null, 0.5, null, null, null, null, null, null, null, null, null, null, null, null, 0.8125, null, null, null, null, null, null, null, null, null, null, null, null, 0.6, null, null, null, null, null, null, null, null, null, null, null, null, null, null, null, null, null, null, null, null], "gpr3d_Frankland": [null, null, null, null, null, null, null, null, null, null, null, null, null, null, null, null, null, null, null, null, null, null, null, null, null, null, null, null, null, null, 0.0, null, null, null, null, null, null, null, null, null, null, null, null, null, null, null, null, null, null, null, null, null, null, null], "gpr_Frankland_sum": [0, 0.5, 0, 0, 0.5, 0, 0, 1.0, 0, 0, 0, 0.625, 0, 0.5, 0, 0, 0.5, 0, 0, 0.6, 0.8125, 0, 0, 0, 0.5, 0, 0, 0.5, 0, 0, 0, 0, 0, 1.1, 0, 0, 0.5, 0, 0, 0.5, 0, 0, 0.5, 0, 0, 0.5, 0, 0, 0.5, 0, 0, 0.8, 0, 0], "lbdm_spitch": [null, 0.11255411255411255, 0.021103896103896104, 0.0, 0.021103896103896104, 0.04220779220779221, 0.07034632034632034, 0.28138528138528135, 0.1085343228200371, 0.03014842300556586, 0.04220779220779221, 0.04220779220779221, 0.04220779220779221, 0.04220779220779221, 0.04220779220779221, 0.04220779220779221, 0.0, 0.0, 0.10551948051948051, 0.0, 1.0, 0.12175324675324677, 0.10551948051948051, 0.08039579468150897, 0.18089053803339517, 0.10551948051948051, 0.052759740259740256, 0.04220779220779221, 0.021103896103896104, 0.021103896103896104, 0.04220779220779221, 0.0, 0.07034632034632034, 0.3517316017316017, 0.11255411255411255, 0.07386363636363635, 0.2637987012987013, 0.17586580086580084, 0.07034632034632034, 0.04220779220779221, 0.021103896103896104, 0.0, 0.021103896103896104, 0.04220779220779221, 0.04220779220779221, 0.04220779220779221, 0.04220779220779221, 0.0, 0.0, 0.0, 0.10551948051948051, 0.0, null, null], "lbdm_sioi": [null, 0.21874999999999997, 0.08680555555555555, 0.11111111111111112, 0.21874999999999997, 0.08680555555555555, 0.11111111111111112, 0.21874999999999997, 0.052083333333333336, 0.0, 0.0625, 0.3888888888888889, 0.11111111111111112, 0.21874999999999997, 0.08680555555555555, 0.11111111111111112, 0.21874999999999997, 0.08680555555555555, 0.19444444444444445, 0.6190476190476191, 0.08928571428571429, 0.12500000000000003, 0.22222222222222224, 0.1736111111111111, 0.43749999999999994, 0.22222222222222224, 0.11111111111111112, 0.21874999999999997, 0.08680555555555555, 0.06944444444444445, 0.0, 0.0, 0.10416666666666667, 0.43749999999999994, 0.22222222222222224, 0.1736111111111111, 0.43749999999999994, 0.22222222222222224, 0.11111111111111112, 0.21874999999999997, 0.08680555555555555, 0.11111111111111112, 0.21874999999999997, 0.08680555555555555, 0.11111111111111112, 0.21874999999999997, 0.08680555555555555, 0.11111111111111112, 0.21874999999999997, 0.08680555555555555, 0.19444444444444445, 1.0, null, null], "lbdm_srest": [null, 0.0, 0.0, 0.0, 0.0, 0.0, 0.0, 0.0, 0.0, 0.0, 0.0, 0.0, 0.0, 0.0, 0.0, 0.0, 0.0, 0.0, 0.0, 0.0, 0.0, 0.0, 0.0, 0.0, 0.0, 0.0, 0.0, 0.0, 0.0, 0.0, 0.0, 0.0, 0.0, 0.0, 0.0, 0.0, 0.0, 0.0, 0.0, 0.0, 0.0, 0.0, 0.0, 0.0, 0.0, 0.0, 0.0, 0.0, 0.0, 0.0, 0.0, 0.0, null, null], "lbdm_rpitch": [null, 0.3333333333333333, 0.2, 0.0, 0.0, 0.2, 0.0, 0.3333333333333333, 0.2, 0.14285714285714285, 0.0, 0.2, 0.2, 0.0, 0.2, 0.2, 0.0, 0.0, 0.0, 0.5, 0.8, 0.38461538461538464, 0.0, 0.3333333333333333, 0.42857142857142855, 0.0, 0.25, 0.0, 0.2, 0.0, 0.2, 0.0, 0.0, 0.3333333333333333, 0.3333333333333333, 0.2, 0.5, 0.0, 0.3333333333333333, 0.0, 0.2, 0.0, 0.0, 0.2, 0.0, 0.2, 0.2, 0.0, 0.0, 0.0, 0.0, 0.5, 0.0, null], "lbdm_rioi": [null, 0.2, 0.5, 0.3333333333333333, 0.2, 0.5, 0.3333333333333333, 0.2, 0.5, 0.0, 0.0, 0.6, 0.3333333333333333, 0.2, 0.5, 0.3333333333333333, 0.2, 0.5, 0.3333333333333333, 0.6, 0.14285714285714285, 0.0, 0.2, 0.3333333333333333, 0.5, 0.2, 0.3333333333333333, 0.2, 0.5, 0.3333333333333333, 0.0, 0.0, 0.0, 0.5, 0.2, 0.3333333333333333, 0.5, 0.2, 0.3333333333333333, 0.2, 0.5, 0.3333333333333333, 0.2, 0.5, 0.3333333333333333, 0.2, 0.5, 0.3333333333333333, 0.2, 0.5, 0.3333333333333333, 0.6, 0.6, null], "lbdm_rrest": [null, 0.0, 0.0, 0.0, 0.0, 0.0, 0.0, 0.0, 0.0, 0.0, 0.0, 0.0, 0.0, 0.0, 0.0, 0.0, 0.0, 0.0, 0.0, 0.0, 0.0, 0.0, 0.0, 0.0, 0.0, 0.0, 0.0, 0.0, 0.0, 0.0, 0.0, 0.0, 0.0, 0.0, 0.0, 0.0, 0.0, 0.0, 0.0, 0.0, 0.0, 0.0, 0.0, 0.0, 0.0, 0.0, 0.0, 0.0, 0.0, 0.0, 0.0, 0.0, 0.0, null], "lbdm_boundarystrength": [null, 0.13751352813852813, 0.0486787518037518, 0.05555555555555556, 0.11465097402597402, 0.053954725829725825, 0.07314213564213565, 0.17972132034632032, 0.05317524737167594, 0.007537105751391465, 0.04180194805194805, 0.2049963924963925, 0.06610750360750361, 0.11992694805194803, 0.053954725829725825, 0.06610750360750361, 0.10937499999999999, 0.043402777777777776, 0.12360209235209235, 0.30952380952380953, 0.29464285714285715, 0.09293831168831171, 0.13749098124098125, 0.1069045042259328, 0.26397263450834874, 0.13749098124098125, 0.06874549062049062, 0.11992694805194803, 0.0486787518037518, 0.03999819624819625, 0.010551948051948052, 0.0, 0.06966991341991342, 0.30668290043290036, 0.13924963924963926, 0.10527146464646464, 0.2846996753246753, 0.15507756132756134, 0.07314213564213565, 0.11992694805194803, 0.0486787518037518, 0.05555555555555556, 0.11465097402597402, 0.053954725829725825, 0.06610750360750361, 0.11992694805194803, 0.053954725829725825, 0.05555555555555556, 0.10937499999999999, 0.043402777777777776, 0.12360209235209235, 0.5, null, null]}}
