{"id": "NLB143652_01", "tunefamily": "", "year": 1941, "tunefamily_full": "", "type": "vocal", "freemeter": false, "origin": "", "features": {"scaledegree": [1, 1, 1, 3, 3, 5, 5, 5, 6, 7, 1, 5, 1, 1, 1, 7, 6, 6, 5, 3, 3, 5, 4, 3, 2, 1], "scaledegreespecifier": ["P", "P", "P", "M", "M", "P", "P", "P", "M", "M", "P", "P", "P", "P", "P", "M", "M", "M", "P", "M", "M", "P", "P", "M", "M", "P"], "tonic": ["C", "C", "C", "C", "C", "C", "C", "C", "C", "C", "C", "C", "C", "C", "C", "C", "C", "C", "C", "C", "C", "C", "C", "C", "C", "C"], "mode": ["major", "major", "major", "major", "major", "major", "major", "major", "major", "major", "major", "major", "major", "major", "major", "major", "major", "major", "major", "major", "major", "major", "major", "major", "major", "major"], "metriccontour": [null, "-", "=", "+", "-", "+", "-", "-", "+", "-", "+", "-", "+", "-", "+", "-", "+", "-", "+", "+", "-", "+", "-", "+", "-", "+"], "imaweight": [0.983193, 0.138655, 0.0378151, 1.0, 0.0336134, 0.962185, 0.962185, 0.0504202, 0.945378, 0.962185, 0.945378, 0.978992, 0.945378, 0.0714286, 0.945378, 0.0336134, 0.945378, 0.0546218, 0.945378, 0.945378, 0.0546218, 0.945378, 0.0504202, 0.945378, 0.0546218, 0.945378], "imaweight_spectral": [0.92126, 0.129921, 0.102362, 0.937008, 0.0984252, 0.937008, 0.952756, 0.129921, 0.92126, 0.952756, 0.92126, 1.0, 0.92126, 0.133858, 0.937008, 0.114173, 0.92126, 0.102362, 0.952756, 0.937008, 0.102362, 0.937008, 0.161417, 0.92126, 0.102362, 0.952756], "pitch40_hewlett": [123, 123, 123, 135, 135, 146, 146, 146, 152, 158, 163, 146, 163, 163, 163, 158, 152, 152, 146, 135, 135, 146, 140, 135, 129, 123], "pitch40_sapp": [162, 162, 162, 174, 174, 185, 185, 185, 191, 197, 202, 185, 202, 202, 202, 197, 191, 191, 185, 174, 174, 185, 179, 174, 168, 162], "octave": [4, 4, 4, 4, 4, 4, 4, 4, 4, 4, 5, 4, 5, 5, 5, 4, 4, 4, 4, 4, 4, 4, 4, 4, 4, 4], "midipitch": [60, 60, 60, 64, 64, 67, 67, 67, 69, 71, 72, 67, 72, 72, 72, 71, 69, 69, 67, 64, 64, 67, 65, 64, 62, 60], "diatonicpitch": [28, 28, 28, 30, 30, 32, 32, 32, 33, 34, 35, 32, 35, 35, 35, 34, 33, 33, 32, 30, 30, 32, 31, 30, 29, 28], "diatonicinterval": [null, 0, 0, 2, 0, 2, 0, 0, 1, 1, 1, -3, 3, 0, 0, -1, -1, 0, -1, -2, 0, 2, -1, -1, -1, -1], "chromaticinterval": [null, 0, 0, 4, 0, 3, 0, 0, 2, 2, 1, -5, 5, 0, 0, -1, -2, 0, -2, -3, 0, 3, -2, -1, -2, -2], "pitchproximity": [null, null, 0, 4, 0, 3, 0, 0, 2, 2, 1, 5, 5, 0, 0, 1, 2, 0, 2, 3, 0, 3, 2, 1, 2, 2], "pitchreversal": [null, null, 0, 0, 0, 0, 0, 0, 0, 0, 0, 0, 1.5, 0, 0, 0, 0, 0, 0, 0, 0, 0, 1.5, 0, 0, 0], "nextisrest": [false, false, false, false, false, false, false, false, false, false, false, false, false, false, false, false, false, false, false, false, false, false, false, false, false, true], "restduration_frac": [null, null, null, null, null, null, null, null, null, null, null, null, null, null, null, null, null, null, null, null, null, null, null, null, null, "1/2"], "duration": [0.5, 0.5, 0.5, 1.0, 0.5, 1.5, 1.0, 0.5, 1.5, 1.5, 1.5, 1.5, 1.0, 0.5, 1.0, 0.5, 1.0, 0.5, 1.5, 1.0, 0.5, 1.0, 0.5, 1.0, 0.5, 1.0], "duration_frac": ["1/2", "1/2", "1/2", "1", "1/2", "3/2", "1", "1/2", "3/2", "3/2", "3/2", "3/2", "1", "1/2", "1", "1/2", "1", "1/2", "3/2", "1", "1/2", "1", "1/2", "1", "1/2", "1"], "duration_fullname": ["Eighth", "Eighth", "Eighth", "Quarter", "Eighth", "Dotted Quarter", "Quarter", "Eighth", "Dotted Quarter", "Dotted Quarter", "Dotted Quarter", "Dotted Quarter", "Quarter", "Eighth", "Quarter", "Eighth", "Quarter", "Eighth", "Dotted Quarter", "Quarter", "Eighth", "Quarter", "Eighth", "Quarter", "Eighth", "Quarter"], "durationcontour": [null, "=", "=", "+", "-", "+", "-", "-", "+", "=", "=", "=", "-", "-", "+", "-", "+", "-", "+", "-", "-", "+", "-", "+", "-", "+"], "onsettick": [0, 1, 2, 3, 5, 6, 9, 11, 12, 15, 18, 21, 24, 26, 27, 29, 30, 32, 33, 36, 38, 39, 41, 42, 44, 45], "beatfraction": ["1/3", "1/3", "1/3", "2/3", "1/3", "1", "2/3", "1/3", "1", "1", "1", "1", "2/3", "1/3", "2/3", "1/3", "2/3", "1/3", "1", "2/3", "1/3", "2/3", "1/3", "2/3", "1/3", "2/3"], "phrasepos": [0.0, 0.1111111111111111, 0.2222222222222222, 0.3333333333333333, 0.5555555555555556, 0.6666666666666666, 1.0, 0.0, 0.1, 0.4, 0.7, 1.0, 0.0, 0.2222222222222222, 0.3333333333333333, 0.5555555555555556, 0.6666666666666666, 0.8888888888888888, 1.0, 0.0, 0.2222222222222222, 0.3333333333333333, 0.5555555555555556, 0.6666666666666666, 0.8888888888888888, 1.0], "phrase_ix": [0, 0, 0, 0, 0, 0, 0, 1, 1, 1, 1, 1, 2, 2, 2, 2, 2, 2, 2, 3, 3, 3, 3, 3, 3, 3], "phrase_end": [false, false, false, false, false, false, true, false, false, false, false, true, false, false, false, false, false, false, true, false, false, false, false, false, false, true], "songpos": [0.0, 0.022222222222222223, 0.044444444444444446, 0.06666666666666667, 0.1111111111111111, 0.13333333333333333, 0.2, 0.24444444444444444, 0.26666666666666666, 0.3333333333333333, 0.4, 0.4666666666666667, 0.5333333333333333, 0.5777777777777777, 0.6, 0.6444444444444445, 0.6666666666666666, 0.7111111111111111, 0.7333333333333333, 0.8, 0.8444444444444444, 0.8666666666666667, 0.9111111111111111, 0.9333333333333333, 0.9777777777777777, 1.0], "beatinsong": ["0", "1/3", "2/3", "1", "5/3", "2", "3", "11/3", "4", "5", "6", "7", "8", "26/3", "9", "29/3", "10", "32/3", "11", "12", "38/3", "13", "41/3", "14", "44/3", "15"], "beatinphrase": ["0", "1/3", "2/3", "1", "5/3", "2", "3", "-1/3", "0", "1", "2", "3", "0", "2/3", "1", "5/3", "2", "8/3", "3", "0", "2/3", "1", "5/3", "2", "8/3", "3"], "beatinphrase_end": ["-2", "-5/3", "-4/3", "-1", "-1/3", "0", "1", "-7/3", "-2", "-1", "0", "1", "-2", "-4/3", "-1", "-1/3", "0", "2/3", "1", "-2", "-4/3", "-1", "-1/3", "0", "2/3", "1"], "IOI_frac": ["1/2", "1/2", "1/2", "1", "1/2", "3/2", "1", "1/2", "3/2", "3/2", "3/2", "3/2", "1", "1/2", "1", "1/2", "1", "1/2", "3/2", "1", "1/2", "1", "1/2", "1", "1/2", "3/2"], "IOI": [0.5, 0.5, 0.5, 1.0, 0.5, 1.5, 1.0, 0.5, 1.5, 1.5, 1.5, 1.5, 1.0, 0.5, 1.0, 0.5, 1.0, 0.5, 1.5, 1.0, 0.5, 1.0, 0.5, 1.0, 0.5, 1.5], "IOR_frac": [null, "1", "1", "2", "1/2", "3", "2/3", "1/2", "3", "1", "1", "1", "2/3", "1/2", "2", "1/2", "2", "1/2", "3", "2/3", "1/2", "2", "1/2", "2", "1/2", "3"], "IOR": [null, 1.0, 1.0, 2.0, 0.5, 3.0, 0.6666666666666666, 0.5, 3.0, 1.0, 1.0, 1.0, 0.6666666666666666, 0.5, 2.0, 0.5, 2.0, 0.5, 3.0, 0.6666666666666666, 0.5, 2.0, 0.5, 2.0, 0.5, 3.0], "imacontour": [null, "-", "-", "+", "-", "+", "=", "-", "+", "+", "-", "+", "-", "-", "+", "-", "+", "-", "+", "=", "-", "+", "-", "+", "-", "+"], "pitch": ["C4", "C4", "C4", "E4", "E4", "G4", "G4", "G4", "A4", "B4", "C5", "G4", "C5", "C5", "C5", "B4", "A4", "A4", "G4", "E4", "E4", "G4", "F4", "E4", "D4", "C4"], "contour3": [null, "=", "=", "+", "=", "+", "=", "=", "+", "+", "+", "-", "+", "=", "=", "-", "-", "=", "-", "-", "=", "+", "-", "-", "-", "-"], "contour5": [null, "=", "=", "++", "=", "++", "=", "=", "+", "+", "+", "--", "++", "=", "=", "-", "-", "=", "-", "--", "=", "++", "-", "-", "-", "-"], "beatstrength": [1.0, 0.25, 0.25, 0.5, 0.25, 1.0, 0.5, 0.25, 1.0, 0.5, 1.0, 0.5, 1.0, 0.25, 0.5, 0.25, 1.0, 0.25, 0.5, 1.0, 0.25, 0.5, 0.25, 1.0, 0.25, 0.5], "beat_str": ["1", "1", "1", "2", "2", "1", "2", "2", "1", "2", "1", "2", "1", "1", "2", "2", "1", "1", "2", "1", "1", "2", "2", "1", "1", "2"], "beat_fraction_str": ["0", "1/3", "2/3", "0", "2/3", "0", "0", "2/3", "0", "0", "0", "0", "0", "2/3", "0", "2/3", "0", "2/3", "0", "0", "2/3", "0", "2/3", "0", "2/3", "0"], "beat": [1.0, 1.3333333333333333, 1.6666666666666667, 2.0, 2.6666666666666665, 1.0, 2.0, 2.6666666666666665, 1.0, 2.0, 1.0, 2.0, 1.0, 1.6666666666666667, 2.0, 2.6666666666666665, 1.0, 1.6666666666666667, 2.0, 1.0, 1.6666666666666667, 2.0, 2.6666666666666665, 1.0, 1.6666666666666667, 2.0], "timesignature": ["6/8", "6/8", "6/8", "6/8", "6/8", "6/8", "6/8", "6/8", "6/8", "6/8", "6/8", "6/8", "6/8", "6/8", "6/8", "6/8", "6/8", "6/8", "6/8", "6/8", "6/8", "6/8", "6/8", "6/8", "6/8", "6/8"], "gpr2a_Frankland": [null, null, null, null, null, null, null, null, null, null, null, null, null, null, null, null, null, null, null, null, null, null, null, null, null, 0.125], "gpr2b_Frankland": [null, null, null, 0.5, null, 0.5, null, null, null, null, null, null, null, null, 0.5, null, 0.5, null, 0.5, null, null, 0.5, null, 0.5, null, null], "gpr3a_Frankland": [null, null, 1.0, null, 1.0, null, null, null, null, null, null, null, null, null, null, 0.75, null, null, 0.6666666666666667, null, 0.6666666666666667, null, null, null, null, null], "gpr3d_Frankland": [null, null, null, null, null, null, null, null, null, 0.0, null, null, null, null, null, null, null, null, null, null, null, null, null, null, null, null], "gpr_Frankland_sum": [0, 0, 1.0, 0.5, 1.0, 0.5, 0, 0, 0, 0, 0, 0, 0, 0, 0.5, 0.75, 0.5, 0, 1.1666666666666667, 0, 0.6666666666666667, 0.5, 0, 0.5, 0, 0.125], "lbdm_spitch": [null, 0.0, 1.0, 0.0, 0.6749999999999999, 0.0, 0.0, 0.1875, 0.07500000000000001, 0.13125, 0.46875, 0.6696428571428572, 0.0, 0.0, 0.1, 0.2625, 0.0, 0.24107142857142855, 0.41785714285714287, 0.0, 0.41785714285714287, 0.1285714285714286, 0.07500000000000001, 0.07500000000000001, null, null], "lbdm_sioi": [null, 0.0, 0.15873015873015875, 0.634920634920635, 0.39682539682539686, 1.0, 0.507936507936508, 0.39682539682539686, 0.7142857142857144, 0.0, 0.0, 0.2857142857142858, 0.507936507936508, 0.3174603174603175, 0.634920634920635, 0.3174603174603175, 0.634920634920635, 0.39682539682539686, 1.0, 0.507936507936508, 0.3174603174603175, 0.634920634920635, 0.3174603174603175, 0.634920634920635, null, null], "lbdm_srest": [null, 0.0, 0.0, 0.0, 0.0, 0.0, 0.0, 0.0, 0.0, 0.0, 0.0, 0.0, 0.0, 0.0, 0.0, 0.0, 0.0, 0.0, 0.0, 0.0, 0.0, 0.0, 0.0, 0.0, null, null], "lbdm_rpitch": [null, 0.0, 0.6666666666666666, 0.6666666666666666, 0.6, 0.6, 0.0, 0.5, 0.0, 0.2, 0.5, 0.0, 0.7142857142857143, 0.0, 0.3333333333333333, 0.2, 0.5, 0.5, 0.14285714285714285, 0.6, 0.6, 0.14285714285714285, 0.2, 0.2, 0.0, null], "lbdm_rioi": [null, 0.0, 0.0, 0.3333333333333333, 0.3333333333333333, 0.5, 0.2, 0.3333333333333333, 0.5, 0.0, 0.0, 0.0, 0.2, 0.3333333333333333, 0.3333333333333333, 0.3333333333333333, 0.3333333333333333, 0.3333333333333333, 0.5, 0.2, 0.3333333333333333, 0.3333333333333333, 0.3333333333333333, 0.3333333333333333, 0.3333333333333333, null], "lbdm_rrest": [null, 0.0, 0.0, 0.0, 0.0, 0.0, 0.0, 0.0, 0.0, 0.0, 0.0, 0.0, 0.0, 0.0, 0.0, 0.0, 0.0, 0.0, 0.0, 0.0, 0.0, 0.0, 0.0, 0.0, 0.0, null], "lbdm_boundarystrength": [null, 0.0, 0.32936507936507936, 0.3174603174603175, 0.36716269841269844, 0.5, 0.253968253968254, 0.24528769841269843, 0.3758928571428572, 0.0328125, 0.1171875, 0.3102678571428572, 0.253968253968254, 0.15873015873015875, 0.3424603174603175, 0.22435515873015877, 0.3174603174603175, 0.2586805555555556, 0.6044642857142857, 0.253968253968254, 0.26319444444444445, 0.34960317460317464, 0.17748015873015877, 0.3362103174603175, null, null]}, "ann_bgcorpus": false}
